{
  "title": "蜃気楼",
  "original_title": null,
  "author": "芥川龍之介",
  "translator": null,
  "country": "日本",
  "genre": "短編小説",
  "subgenre": [
    "心理小説",
    "幻想文学",
    "純文学"
  ],
  "publication_year": 1927,
  "japanese_publication_year": 1927,
  "summary": "1927年3月に雑誌『婦人公論』で発表された短編小説です。神経衰弱に悩む主人公「僕」が、友人のKとOとともに鵠沼海岸で蜃気楼を見に行く物語です。昼間の蜃気楼探索では青い陽炎と水葬者の遺品と思われる木札を発見し、夜間の再訪では幻聴や幻覚に襲われます。起承転結に乏しく、事件らしい事件が起こらない平坦な構成が特徴で、妻とOの優しさに支えられながらも、不気味さと死の気配が漂う作品です。詩的精神を重視した芥川が、「小説の筋」論争の中で実践した、ストーリー性を排除した新しい小説形式を示しています。",
  "tags": [
    "心理描写",
    "幻覚と幻聴",
    "死のテーマ",
    "詩的表現",
    "晩年の傑作"
  ],
  "source_urls": [
    "https://ara-suji.com/novel/4320/",
    "https://jun-bungaku.jp/sinkirou/",
    "https://bookmeter.com/books/5668035"
  ],
  "book_id": 147,
  "generated_at": "2026-05-09T20:59:22.220854+00:00"
}