{
  "contents": {
    "content_0.html": {
      "headings": [],
      "summary": "教師の保吉やすきは、以前から店主と親しくしていた馴染みの店へ通っている。かつては眇目の無愛想な店主のみがいたが、ある日、猫のような顔をした若い女が店を預かるようになる。保吉は女が不慣れで失敗する様子に懐かしさを感じ、後に嘘をついてココアの存在を確かめるなど、彼女を「含羞草」として弄ぶような心理を抱くようになる。しかし、秋に女と主人が「ゼンマイ珈琲」の話をしている姿を見て、そこに天使の姿を感じ、女への感情に変化が生じる。その後、女は姿を消すが、二月の末、女が赤子を抱えて店前に現れる。保吉は、羞恥心の強い娘から、子供のために堂々とした母へと変容した彼女の姿を見て、古来どのような悪事も犯し得る「母」という存在の恐ろしさと尊厳を再認識し、春の月を見上げながら深く感銘を受ける。"
    }
  },
  "overall": {
    "summary": "かつて瞳を患った店主の店に、猫のような顔をした若い女が現れる。教師の保吉やすきは、彼女が不慣れで失敗する様子や、彼が嘘をついてココアの有無を試すなど、彼女を「含羞草」として弄ぶような心理を抱いていた。しかし、女が主人と共に「ゼンマイ珈琲」について語り合う姿に天使の姿を重ね、感情に変化を覚える。その後女は姿を消すが、二月末、彼女が赤子を抱えて店先に現れる。羞恥心の強い娘から、子供のために堂々とした母へと変容した姿に、保吉は古来どのような悪事も犯し得る「母」という存在の恐ろしさと尊厳を再認識し、春の月を見上げて深く感銘を受ける。本作品は、人間の心の機微や他者との葛藤、そして母性という根源的な力への畏敬を、静謐かつ詩的な筆致で描き出す傑作である。登場人物の内面の変化が繊細に描かれる読み応えと、日常の些細な出来事から人生の深層を浮き彫りする作者独自の魅力に満ちている。",
    "tags": {
      "ジャンル": [
        "短編小説"
      ],
      "時代": [],
      "文学運動・流派": [],
      "テーマ": [
        "心理描写",
        "母・父・子の関係",
        "孤独・疎外",
        "人間の内面・自我"
      ],
      "形式・文体": [
        "詩的散文"
      ]
    }
  }
}