{
  "book_id": 792,
  "title": "思い出す事など 他七篇",
  "author": "夏目漱石",
  "translator": null,
  "country": "日本",
  "publication_year": null,
  "summary": "本作は夏目漱石による八篇のエッセー・随筆を収録した作品です。表題作「思い出す事など」をはじめとする各篇では、著者が自身の過去の思い出や経験、人物観察などを綴っています。漱石の独特な視点から描かれる人間関係や人生経験は、知性的かつ洞察に満ちた文体で表現されており、読者に深い思考の場をもたらします。岩波文庫の緑版として出版されており、日本の近代文学を代表する知識人による省察的な随筆集として位置づけられています。漱石の思想的深さと文学的洗練さが顕著に現れた作品です。",
  "tags": {
    "ジャンル": [
      "随筆・エッセイ"
    ],
    "時代": [
      "明治文学"
    ],
    "文学運動・流派": [],
    "テーマ": [
      "知識人の苦悩",
      "心理描写"
    ],
    "形式・文体": []
  },
  "source_urls": [
    "https://bookmeter.com/books/541366",
    "https://www.amazon.co.jp/%E6%80%9D%E3%81%84%E5%87%BA%E3%81%99%E4%BA%8B%E3%81%AA%E3%81%A9-%E4%BB%96%E4%B8%83%E7%AF%87-%E5%B2%A9%E6%B3%A2%E6%96%87%E5%BA%AB-%E5%A4%8F%E7%9B%AE-%E6%BC%B1%E7%9F%B3/dp/4003101162",
    "https://www.aozora.gr.jp/cards/000148/files/792_14937.html"
  ],
  "generated_at": "2026-05-09T23:45:29.506223+00:00"
}