{
  "book_id": 559,
  "title": "右門捕物帖",
  "author": "佐々木味津三",
  "translator": null,
  "country": "日本",
  "publication_year": 1929,
  "summary": "江戸時代を舞台にした捕物帖シリーズです。主人公の右門は、無口で不愛想な探偵として知られており、和製シャーロック・ホルムスと呼ばれています。全38編以上の短編からなるシリーズで、怪奇事件から人情話まで、江戸の町で起こる様々な謎を鮮やかに解き明かしていきます。本作は嵐寛寿郎による映画化を通じて、キャラクターや設定が磨かれていき、映画と小説が相互に影響し合う独特の発展形態をたどりました。明治から大正にかけての大衆小説の代表作として、現在でも愛され続けています。",
  "tags": {
    "ジャンル": [
      "短編小説",
      "捕物帖",
      "連作短編"
    ],
    "時代": [
      "明治文学",
      "大正文学"
    ],
    "文学運動・流派": [],
    "テーマ": [
      "冒険・活劇",
      "怪談・怪異"
    ],
    "形式・文体": [
      "連作短編"
    ]
  },
  "source_urls": [
    "https://www.aozora.gr.jp/cards/000111/card577.html",
    "https://ja.wikipedia.org/wiki/%E4%BD%90%E3%80%85%E6%9C%A8%E5%91%B3%E6%B4%A5%E4%B8%89",
    "https://www.aozora.gr.jp/index_pages/person111.html"
  ],
  "generated_at": "2026-05-09T23:17:00.666392+00:00"
}