{
  "contents": {
    "content_0.html": {
      "headings": [],
      "summary": "上野博覧会で風船に乗る「私」は、毎回双眼鏡で地上を丹念に漁る謎の西洋人ミハエルと出会う。互いに親しくなり、ミハエルが探し求める「地上の宝」は軍事探偵の正体ではなく、恋に落ちた女性の姿だと明かされる。彼は過去、高所から偶然見かけた美しい日本人女性を求めて博覧会に乗り込み、雨の日も続けたのである。博覧会最終日、晴れた空の下、ミハエルはついに彼女を見つけたと叫ぶ。しかし、「私」が双眼鏡で確認した「彼女」は、印袢天姿の男達に担がれ、象の建物の前で展示されている「飾り付け人形」だった。ミハエルの情熱的な恋心が、風船からの視覚的錯覚によって、単なる人形への執着であったという皮肉な結末を迎える。語り手は始終一人称で、西洋人の悲壮なまでの愛の物語が虚像に基づくものだったと知る瞬間の衝撃を描写している。"
    }
  },
  "overall": {
    "summary": "上野博覧会の高所から、双眼鏡で地上を探索する謎の西洋人ミハエルと出会う一人称の語り手。ミハエルは、過去に偶然見かけた美しい日本人女性の姿を求めて、博覧会初日の風船に乗って以来、連日雨の日も欠かさず地上の宝を捜し続けていた。互いの信頼が深まる中、最終日に晴れた空の下、ついに目標とする女性を見つけたと狂喜するミハエル。しかし、語り手が双眼鏡で確認したそれは、印袢天の男達に担がれ、象の建物の前で展示されていた「飾り付け人形」に過ぎなかった。ミハエルの情熱的な恋心と、その対象が単なる物体への執着であったという事実の対比が、風船からの視覚的錯覚によって引き起こされた悲劇的な皮肉として描かれる。この作品は、高所からの視点がもたらす虚像と真実の乖離、そして幻想的な愛が現実の冷徹な事実に直面する瞬間の衝撃を通じて、愛と虚構、そして人間の知覚の脆さを浮き彫りにする。\n",
    "tags": {
      "ジャンル": [
        "短編小説"
      ],
      "サブジャンル": [
        "幻想・怪奇",
        "叙情的"
      ],
      "時代": [
        "明治文学"
      ],
      "文学運動・流派": [],
      "テーマ": [
        "人間の内面・自我",
        "孤独・疎外",
        "死・生死観"
      ],
      "形式・文体": [
        "独白体"
      ]
    }
  }
}