{
  "contents": {
    "content_0.html": {
      "headings": [],
      "summary": "語り手は北海道・札幌から空知川沿岸の土地調査のため、同僚の案内役である道庁官吏の井田某を探し回る旅に出る。石狩の野を走る汽車や、霧に包まれた森林を走る馬車、そして歌志内の炭山での体験を通じて、語り手は自然の冷厳さと人間の無力さを痛感し、深い孤独に沈む。しかし、歌志内の旅宿主人の親切な話や、鉱夫たちの激しくも哀れな生活の姿に触れることで、人間性の温かさと独立の精神に対する感銘を受け、心が開かれる。翌朝、宿の子の案内で深奥の山道を進み、ついに簡素な掘立小屋にいたる井田某らと面談し、移民用地の選定に成功する。その直後、原始的な深林の中で時雨が降り注ぐ風景に包まれ、語り手は社会や歴史を超えた「生存」そのものの根本を問い、死と隣り合わせたような静寂な威圧感と、それでも冷厳なる自然への渇望を感じ取る展開である。"
    }
  },
  "overall": {
    "summary": "語り手は北海道・札幌から空知川沿岸への土地調査のため、道庁官吏の井田某と合流する旅に出る。石狩の野を走る汽車や、霧に包まれた森林を走る馬車などを通じて自然の冷厳さと人間の無力さを痛感し、深い孤独に沈むが、歌志内の炭山での鉱夫たちの激しくも哀れな生活や、旅宿主人の言葉に触れ、人間性の温かさと独立の精神に感銘を受ける。やがて原始的な深林の掘立小屋で井田と合流し移民用地の選定に成功するが、その直後に降る時雨の中で、語り手は社会や歴史の枠組みを超えた「生存」そのものの根本を問いかける。死と隣り合わせたような静寂な威圧感の中で、冷厳なる自然への渇望と、人間存在の根源的な姿を見つめる体験が描かれる。自然の厳粛さの中で孤独と共生し、人間の小ささと生命の尊厳を対比させる、極めて叙情的かつ哲学的な旅物語である。",
    "tags": {
      "ジャンル": [
        "中編小説"
      ],
      "サブジャンル": [
        "叙情的",
        "哲学的・思索的"
      ],
      "時代": [
        "日本近代文学"
      ],
      "文学運動・流派": [],
      "テーマ": [
        "人間の内面・自我",
        "自然描写",
        "孤独・疎外",
        "死・生死観"
      ],
      "形式・文体": []
    }
  }
}