{
  "contents": {
    "content_0.html": {
      "headings": [],
      "summary": "語り手二人による対話形式で、1920〜30年代のソビエト連邦における旧正月の扱いが詳しく語られる。相手は日本の祝祭やクリスマスとの違いを尋ね、語り手はソビエトでは宗教撲滅により正月行事が廃止され、代わりに労働者階級の視点から1929年に「5日週制」という革命暦が導入されたことを説明する。元旦は労働日であり、真の祭日はプロレタリアートの記念日である「血の日曜日（1月9日）」のみであることが示される。また、アルコール中毒撲滅運動や、女性労働者が託児所の支援を得てクラブで集会に参加する社会制度の充実など、生産性向上と階級意識の強化を背景とした生活様式が描かれる。この対話を通じて、私的・宗教的祝祭を排し、集団的・政治的な行事を重視するソビエト社会の姿が浮き彫りにされる。語り手は特定の人物名はないが、ソビエト事情に詳しい者からの報告という立場を貫いており、視点の変更はない。"
    }
  },
  "overall": {
    "summary": "本書は、語り手二人の対話形式で構成された短編であり、1920〜30年代のソビエト連邦における旧正月の扱いと社会制度の変容を主題としている。対話の中心では、日本の祝祭やクリスマスとは異なり、宗教撲滅政策により伝統的な正月行事が廃止され、代わりに労働者階級の視点から1929年に「5日週制」が導入された革命暦が採用された実態が語られる。元旦は通常通り労働日であり、真の祭日は「血の日曜日（1月9日）」といったプロレタリアートの記念日のみである。アルコール中毒撲滅運動や、女性労働者が託児所の支援を得てクラブに参加できる社会制度の充実など、生産性向上と階級意識の強化を背景とした生活様式が詳細に描かれる。私的・宗教的祝祭を排し、集団的・政治的な行事を重視するソビエト社会の姿が、具体的な制度の変化を通じて浮き彫りにされる。作品は特定の個人の感情移入を避け、客観的な社会報告としての性質を強く持ち、旧体制からの脱却と新体制の構築という時代の変革の過程を、祝祭という視点から浮き彫りに描き出している。",
    "tags": {
      "ジャンル": [
        "短編小説"
      ],
      "サブジャンル": [
        "時代小説"
      ],
      "時代": [
        "昭和文学"
      ],
      "文学運動・流派": [],
      "テーマ": [
        "社会批評・風刺",
        "知識人の苦悩"
      ],
      "形式・文体": [
        "書簡体・日記形式"
      ]
    }
  }
}