{
  "contents": {
    "content_0.html": {
      "headings": [],
      "summary": "昭和七年十二月の寒い日、語り手は帰宅の途上で障子に藤豆が飛び込み衝突する現象を目撃する。庭の藤棚や台所前の藤ともが一斉に実を弾き飛ばすこの事象は、極度の乾燥によるものであり、豆のさやに潜む物理的な爆発力が驚嘆に値するものとして分析される。語り手はこれを「潮時」と呼ぶ自然の同期現象と捉え、春の椿の花落ちや秋の銀杏の葉散りなどにも同様の不連続的な同時発生の例があることを指摘する。これら植物現象は、風がなくても一斉に起こるため、目に見えぬ何かの仕掛けのように思われる。次に語り手は、自家で連続して子供たちの事故や盗難、器物の紛失といった不幸が相次ぐ出来事を、自然現象の偶然性との対比の中で考察する。これらが純粋な偶然なのか、あるいは科学的に説明可能な「悪日」や統計的な不連続線に伴うものであるのかは断定できないが、迷信とされる人事の不連続も、将来の科学によって解明される可能性を示唆する。語り手は自身の物理学徒としての視点から、植物界の物理法則と人間の運命の偶然性・必然性の境界を問う。"
    }
  },
  "overall": {
    "summary": "明治から大正、昭和にかけて活躍した科学者・作家の寺田寅彦が、自身の物理学的な視点を交えて綴った随筆風小説である。語り手が帰宅の途上で目撃した、乾燥した冬日に藤のさやが不意に弾けて豆を飛散させる現象をきっかけに、自然の非連続的な同期現象について考察を深めていく。春の椿花落ちや秋の銀杏散りなどと同様に、風も吹かずとも一斉に起こるこの事象は、目に見えぬ何らかの仕掛けを思わせる一方で、物理法則に基づく必然的な現象として捉え直される。語り手は、この自然現象と連続する人間の不幸、すなわち事故や盗難などの人事の不連続性を対比させながら、迷信とされる偶然や不運が、将来の科学によって解明される可能性を示唆する。科学者としての冷静な観察眼と、自然と人間の運命の境界線に対する哲学的な問いかけが交錯する中で、作者は自然の神秘と人間の知性の狭間で揺れる現代人の視点を鮮やかに描き出す。自然の微細な動きから普遍的な真理へと思索を飛躍させる、短くも深遠な珠玉の作品である。",
    "tags": {
      "ジャンル": [
        "随筆・エッセイ"
      ],
      "時代": [
        "大正文学"
      ],
      "文学運動・流派": [],
      "テーマ": [
        "哲学・思想",
        "自然描写",
        "知識人の苦悩"
      ],
      "形式・文体": []
    }
  }
}