{
  "book_id": 674,
  "title": "ぢいさんばあさん",
  "author": "森鴎外",
  "translator": null,
  "country": "日本",
  "publication_year": 1915,
  "summary": "大正4年（1915）に発表された森鴎外の短編小説です。江戸時代の文人・大田南畝の随筆『一話一言』に記された史料を基に創作されました。麻布竜土町に隠居する老夫婦・美濃部伊織とるんの37年に及ぶ波乱万丈の人生を描きます。若き日に刀をめぐる事件から伊織が越前へ流刑となり、るんが黒田家での長年の奉公を経て、晩年になって再会するまでの夫婦の絆と貞節の物語です。江戸幕府の時代背景の中で、真摯に人生を歩んだ夫婦の深い愛情と忍耐が印象的です。",
  "tags": {
    "ジャンル": [
      "短編小説",
      "歴史小説"
    ],
    "時代": [
      "江戸文学",
      "明治文学"
    ],
    "文学運動・流派": [],
    "テーマ": [
      "家族・人間関係",
      "恋愛・純愛"
    ],
    "形式・文体": []
  },
  "source_urls": [
    "https://www.aozora.gr.jp/cards/000129/files/674_15358.html",
    "https://bungakublog.com/moriougai-jisanbasan-top",
    "https://yazoolife.com/archives/859"
  ],
  "generated_at": "2026-05-09T23:31:20.311852+00:00"
}