{
  "title": "捨児",
  "original_title": null,
  "author": "芥川龍之介",
  "translator": null,
  "country": "日本",
  "genre": "短編小説",
  "subgenre": [
    "心理小説",
    "人情小説",
    "道徳小説"
  ],
  "publication_year": null,
  "japanese_publication_year": null,
  "summary": "浅草の信行寺の住職・日錚和尚が、寺の門前に捨てられていた男の子を拾い、勇之助と名付けて育てます。明治二十七年の冬、三十四五の女性が現れ、自分がこの子の母親だと名乗ります。彼女は、夫の株の失敗で夜逃げを余儀なくされ、泣く泣く子を捨てたこと、その後の苦労と、夫の病死、新しく授かった子の死という悲しみを経験し、捨てた長男をどうしても養いたいという願いで寺を訪ねたのだと説明します。和尚は勇之助を母親に引き取らせます。しかし成長した勇之助が後に知らされたのは、その女性が本当の母親ではなく、実は子どもを亡くしたことすら嘘だったという事実です。にもかかわらず勇之助は、その女性に対してより一層の親愛を感じるようになり、自分の母親以上の人間として敬慕するようになります。血縁を超えた母子の絆と、愛情の本質を問う作品です。",
  "tags": [
    "家族愛",
    "捨児",
    "母子関係",
    "人情",
    "真実と愛"
  ],
  "source_urls": [
    "https://yazoolife.com/archives/3989",
    "https://ja.wikipedia.org/wiki/%E8%8A%A5%E5%B7%9D%E9%BE%8D%E4%B9%8B%E4%BB%8B",
    "http://nobungaku.blogspot.com/2016/01/blog-post_30.html"
  ],
  "book_id": 154,
  "generated_at": "2026-05-09T21:00:29.636715+00:00"
}