{
  "contents": {
    "content_0.html": {
      "headings": [],
      "summary": "語り手は、古来月を愛された詩人たちがなぜ月光に悲しみや郷愁を感じたのかを考察する。月光が遠方にある点と、生物が持つ「向火性」と呼ばれる灯火への本能的な憧憬がその背景にあると説き、人間が火の源を生命の故郷と無意識に結びつける本能を論じる。特に平安貴族らの「騎士道的恋愛」における及ばぬものへの思慕が詩情を深めたとし、これが月歌の隆盛を生んだと分析する。\n\nしかし近代になり詩人が月を忘れ、月光の詩が希少化した原因について、古人の歌い尽くしたマンネリズムや科学による月の物理的な解明（天体観測の進歩）を指摘する。だが語り手は、最も本質的な理由は照明技術の進歩であると結論付ける。防空演習時の真っ暗な都を体験し、電灯に埋もれた日常から月光の明るさを再認識した語り手は、月が詩情を帯びるのは、それよりも遙かに暗い地上での対比にあると悟る。科学と照明の発達により地上が明るくなりすぎてしまった現代では、月という巨大な存在もまた、かつてのような無量の感慨を呼び起こすことができないでいる。"
    }
  },
  "overall": {
    "summary": "語り手は、古来より詩人たちが月を愛し、その光に悲しみや郷愁を感じてきた理由を探る。月は遠く離れている点に加え、人間が火への本能的な憧憬（向火性）を持っていることから、月は生命の故郷へと繋がれる象徴となり、平安貴族の騎士道的恋愛のように及ばぬものへの思慕を深めてきたと説く。しかし近代に入り、月を詠む詩が激減した原因について、単なるマンネリズムや天体観測による月の物理的解明のみならず、最も本質的な要因は照明技術の進歩にあると結論付ける。防空演習時の闇と、電灯に囲まれた現代の日常を対比させた語り手は、月が詩情を帯びるのは、それよりも遙かに暗い地上でのみ成立するものだと悟る。科学と人工照明の発達により地上が過度に明るくなり、月という巨大な存在がかつてのような無量の感慨を呼び起こすことを阻んでいるという、現代の視点を提示する。",
    "tags": {
      "ジャンル": [
        "エッセイ"
      ],
      "サブジャンル": [
        "叙情的"
      ],
      "時代": [],
      "文学運動・流派": [],
      "テーマ": [
        "人間の内面・自我",
        "詩的散文"
      ],
      "形式・文体": []
    }
  }
}