{
  "title": "開化の良人",
  "original_title": null,
  "author": "芥川龍之介",
  "translator": null,
  "country": "日本",
  "genre": "短編小説",
  "subgenre": [
    "社会小説",
    "心理小説"
  ],
  "publication_year": 1919,
  "japanese_publication_year": 1919,
  "summary": "明治から大正へと移行する時代に、近代化する日本社会の中で生きる男性を描いた作品です。主人公は、西洋の思想や文化を受け入れようとする「開化」の価値観に影響された人物として描かれています。妻との関係や社会との葛藤を通じて、近代知識人の内面的な苦悩と矛盾が鮮烈に描き出されます。家庭生活における理想と現実のズレ、そして文明開化の波の中で揺らぐ自己のアイデンティティが、芥川特有の鋭い心理描写で表現された作品です。",
  "themes": [
    "近代化と伝統の葛藤",
    "結婚と家庭",
    "知識人の苦悩",
    "文明開化",
    "自己喪失",
    "社会適応"
  ],
  "tags": [
    "短編小説",
    "大正文学",
    "心理描写",
    "社会批評",
    "家庭小説",
    "近代知識人",
    "文明開化"
  ],
  "awards": [],
  "notable_points": "本作は1919年（大正8年）2月に『中央公論』に発表されました。作品のタイトルである「開化の良人」は、西洋思想の影響下にある近代的な男性を指していますが、その内実における矛盾や葛藤が鋭く描かれています。芥川龍之介が近代日本の社会的変化の中で、知識人たちが直面する精神的危機をテーマとした重要な作品の一つです。",
  "source_urls": [
    "https://www.aozora.gr.jp/cards/000879/card67.html",
    "https://ja.wikipedia.org/wiki/%E8%8A%A5%E5%B7%9D%E9%BE%8D%E4%B9%8B%E4%BB%8B"
  ],
  "book_id": 67,
  "generated_at": "2026-05-09T20:41:03.824328+00:00"
}