{
  "contents": {
    "content_0.html": {
      "headings": [
        "ボオドレエルに就いて",
        "ブルジョア芸術に於ける運命",
        "定理",
        "わが終生の祈願",
        "わが友",
        "憂きわれをさびしがらせよ閑古鳥",
        "フィリップの骨格に就いて",
        "或るひとりの男の精進について",
        "生きて行く力",
        "わが唯一のおののき",
        "マンネリズム",
        "作家は小説を書かなければいけない",
        "挨拶",
        "立派ということに就いて",
        "Confiteor",
        "頽廃の児、自然の児"
      ],
      "summary": "この箇所は、日本浪曼派の文学的立場を揺さぶる著者の内省的な断章集である。冒頭、ボオドレールへの抵抗と終生にわたる沈黙への誓いを語った後、シャルル・ルイ・フィリップの作品「小さき町にて」を評し、短命でありながら「厳粛なる半面の大文豪」としてその骨格を称賛する。続く「マンネリズム」の項では、作家が断片的な感想を安易に綴る風潮を厳しく批判し、真の作家としての覚悟を問う。一方で、小説以外の文章を書くことへの葛藤を「立派になりすぎない」ことへの畏れとして吐露し、人間らしさの維持を模索する。終盤では、内村鑑三の随筆に感銘を受け、信仰への一歩を踏み入れた「Confiteor（懺悔）」を記し、自らの言葉のむなしさと沈黙の必要性を告げる。最後に太宰治を「自然の児」と評し、自身の入院という転機を以て生涯の決断を示唆する。語り手は常に一人の作家としての苦悩と自問自答を続ける。"
    }
  },
  "overall": {
    "summary": "本稿は、日本浪曼派の文学的立場に揺さぶりをかけつつ、作家としての内省的な葛藤を描く断章集である。冒頭、ボオドレールへの抵抗を宣言し、シャルル・ルイ・フィリップを「厳粛なる半面の大文豪」と称賛しつつ、自らの沈黙への誓いを語る。続く「マンネリズム」の項では、断片的な感想を安易に綴る風潮を厳しく批判し、真の作家としての覚悟を問いただす一方で、「立派になりすぎない」ことへの畏れとして人間らしさの維持を模索する。終盤では、内村鑑三の随筆に触発され、自らの言葉のむなしさから信仰へと一歩踏み出し、沈黙の必要性を告白する。語り手は常に作家としての苦悩と自問自答を続け、太宰治を「自然の児」と評しつつ、自身の入院という転機を以て生涯の決断を示唆する。文学の真価と作家の在り方への深い思索が、荘厳かつ陰鬱な筆致で綴られる。",
    "tags": {
      "ジャンル": [
        "随筆・エッセイ"
      ],
      "サブジャンル": [
        "哲学的・思索的",
        "叙情的"
      ],
      "時代": [
        "昭和文学"
      ],
      "文学運動・流派": [
        "新思潮派"
      ],
      "テーマ": [
        "人間の内面・自我",
        "心理描写",
        "知識人の苦悩",
        "哲学・思想"
      ],
      "形式・文体": [
        "詩的散文"
      ]
    }
  }
}