{
  "contents": {
    "content_0.html": {
      "headings": [],
      "summary": "語り手は友人から小堀杏奴の『晩年の父』と、鴎外の伝記『安井夫人』を紹介される。鴎外の生涯と娘としての描かれ方、さらに彼が子供に西洋名を付けた様子から、複雑な内部矛盾と家长的な権威を感じ取る。特に、鴎外の芸術的成就と封建的な親子関係の併存、およびそれが子孫の人間性に深く根を下ろしている点に注目する。一方、漱石の死後、遺族や弟子が家父長的な位置づけを強要される現状や、作家の実生活における親子関係が依然として古い形式で支配されている事実に苦痛と危機感を覚える。続いて、島崎蓊助の「父上様」や藤村文学への言及を通じて、作家の私的葛藤と、それが次世代の作家にどのような影響を与え、あるいは圧力となっているかを考察する。特に藤村の長男蓊助の心情や、作家の「自由主義」への期待と現実のズレを指摘し、明治文学における親子関係の重荷と世代間の軋轢を浮き彫りにする。"
    }
  },
  "overall": {
    "summary": "語り手は小堀杏奴や鴎外伝記に触れつつ、明治の文学者たちに見られる家父長制的な親子関係の複雑な実像を深く考察する作品である。鴎外における芸術的成就と封建的権威の併存、あるいは漱死後の弟子たちが強要される家名継承の圧力など、作家の私的葛藤が次世代に重くのしかかる現実が描かれる。特に、島崎藤村の息子蓊助らに表れる期待と現実の亀裂、文学界を支配する古い形式への苦痛が鮮明に浮かび上がる。この作品は、明治文学の光と影をなす「親子関係」を軸に、作家の人間性、世代間の軋轢、そして文学という公共的領域と私的領域の境界線における葛藤を鋭く浮き彫りにする。知識人が直面する家族の重荷と、それが創作活動や人間関係にどう影響するかを思索的・内省的な筆致で描き出し、読者に文学の背後にある人間ドラマと社会的構造を再考させる深い洞察力に満ちている。",
    "tags": {
      "ジャンル": [
        "随筆・エッセイ"
      ],
      "サブジャンル": [
        "叙情的",
        "哲学的・思索的"
      ],
      "時代": [
        "明治文学",
        "昭和文学"
      ],
      "文学運動・流派": [
        "新思潮派"
      ],
      "テーマ": [
        "人間の内面・自我",
        "知識人の苦悩",
        "家族・人間関係",
        "孤独・疎外"
      ],
      "形式・文体": [
        "独白体"
      ]
    }
  }
}