{
  "contents": {
    "content_0.html": {
      "headings": [],
      "summary": "物語の語り手は、生い立ちから多くの親族を失い、生きる苦痛に苛まれる少女 K と、互いの運命を共有する親密な関係にある。秋、二人は湯河原へ逃避行の旅に出る。K は「よい悪事」や「ブルジョア」といった概念を巡り、過去・未来への執着を断ち、ただ今この瞬間を生きることを提案するが、語り手は自らの作家としての虚構性と自殺願望に揺れ動き、混乱を深める。夜の宴席では真実や自己への問いが続くが、語り手は K のまじめな苦しさに触れ、互いの存在を否定し合いながら、深い愛情の中で抱き合う。翌日、雨の湯河原を散歩中に、語り手が K への告白を試みようとする瞬間、バスに轢かれるという予期せぬ事故が起きる。K は軽傷を負うが、語り手は激しく動揺し K を病院へ運ぶ。帰郷後、語り手は K への贈り物として指輪を選び、K はそのお返しに長女の写真を送る。この交流は、絶望と生への執念、そして二人の絆の強さを象徴する結末へと収束する。"
    }
  },
  "overall": {
    "summary": "生い立ちから数々の親族を失い、生きる苦痛に苛まれる少女 K と、彼女を深く愛し共依存関係にある語り手が、秋の湯河原へ逃避行へと旅立つ。語り手は作家としての虚構性や自殺願望に揺れ動き、K は「今この瞬間」への執着を訴えるが、二人は互いの存在を否定し合いながら、深い愛情の中で抱き合う。夜の宴席での真実を巡る議論の後、翌日の雨の散歩道でバスによる予期せぬ事故が発生し、語り手は激しく動揺する。帰郷後、指輪と長女の写真を交換する二人の交流は、絶望と生への執念、そして壊れかけの絆の強さを象徴している。これは、虚構と現実の境界が曖昧になる中、人間の孤独と他者との接続への渇望を描く、痛烈かつ叙情的な物語である。",
    "tags": {
      "ジャンル": [
        "短編小説"
      ],
      "サブジャンル": [
        "耽美派"
      ],
      "時代": [
        "昭和文学"
      ],
      "文学運動・流派": [
        "新思潮派"
      ],
      "テーマ": [
        "人間の内面・自我",
        "孤独・疎外",
        "心理描写"
      ],
      "形式・文体": [
        "独白体"
      ]
    }
  }
}