{
  "title": "みだれ髪",
  "original_title": null,
  "author": "与謝野晶子",
  "translator": null,
  "country": "日本",
  "genre": "歌集",
  "subgenre": [
    "短歌",
    "恋愛詩",
    "浪漫主義文学"
  ],
  "publication_year": 1901,
  "japanese_publication_year": 1901,
  "summary": "与謝野晶子の処女歌集。明治34年（1901年）8月15日に東京新詩社と伊藤文友館の共版で発表されました。編集は与謝野鉄幹が担当し、表紙装丁は藤島武二によるものです。全399首からなり、6つの章に分けられています。鉄幹との激しい恋愛の過程で生まれた本作は、女性の官能性と肉体への大胆な賛美を素直に表現した斬新な作風が特徴です。当時の保守的な道徳観からは徹底的に非難されましたが、上田敏ら文芸評論家からは高く評価され、明治浪漫主義運動の確固たる指標となりました。若い読者の胸に秘めた思いを代弁し、因習的な風土からの自我解放を象徴する作品として、日本文学史上重要な位置を占めています。",
  "tags": [
    "浪漫主義",
    "短歌",
    "恋愛表現",
    "女性文学",
    "明治文学"
  ],
  "source_urls": [
    "https://ja.wikipedia.org/wiki/%E3%81%BF%E3%81%A0%E3%82%8C%E9%AB%AA",
    "https://www.aozora.gr.jp/cards/000885/card548.html",
    "https://www.aozora.gr.jp/cards/000885/files/51307_47033.html"
  ],
  "book_id": 548,
  "generated_at": "2026-05-09T23:16:13.939112+00:00"
}