{
  "contents": {
    "content_0.html": {
      "headings": [],
      "summary": "蒲台出身の劉海石が、幼馴染の義兄弟・劉滄客のもとを訪れる。滄客は長男の死に始まり、妻や義理の娘、召使いらが相次いで死去する絶望的な状況にあった。海石は医術ではなく家相と方位の術を用い、滄客一家の不幸の正体が妾の倪（き）に憑いた狐妖であることを看破する。海石は倪を狐に変身させ首を叩き白髪を抜くが、狐は逃れてしまう。その後、次男夫婦の背の白毛を抜き救済し、さらに家畜の豚の中にも狐が潜伏していることを見抜く。海石は豚から白髪を抜き狐を退治するが、再び脱走を許してしまう。海石は海上での衆生救済のため師匠・山石道人の元へ向かうと語り、別れた後、滄客は海石の本名と山石道人との関係から、彼が仙人の呂洞賓であったと悟る。"
    }
  },
  "overall": {
    "summary": "蒲台出身の劉海石が、災禍に見舞われた幼馴染の劉滄客の家を訪れる物語である。滄客は家族や召使いらが相次いで死亡する絶望的な状況にあったが、海石は医術ではなく家相と方位の術を用い、その原因が妾の倪に憑いた狐妖であることを看破する。海石は倪から白髪を抜き狐を退治しようとするが、狐は何度か逃れてしまう。やがて家畜の豚の中にも狐が潜伏していることを見抜き、そこからも白髪を抜くことで次男夫婦を救い出す。数々の退治の末、海石は海上での衆生救済を約束して去る。別れた後、滄客は海石の本名や師匠の情報を紐解き、彼が仙人の呂洞賓であったと悟る。\n\n本作は、中国古典文学の志怪小説における典型的な仙人譚を踏襲しつつ、狐妖という異界の存在と人間の葛藤を描く幻想文学である。超自然的な現象を冷静な視点で描く文体は、不可解な恐怖と救済の機微を巧みに併存させ、読者に畏怖と安堵の二重の感情をもたらす。特に、術者による退治の過程で描かれる、人間と非人間との境界を曖昧にする世界観は、幻想・怪奇ものの深遠な魅力を示しており、最後に訪れる仙人への覚醒という展開は、読者に神秘的な余韻を残して終わる。",
    "tags": {
      "ジャンル": [
        "短編小説"
      ],
      "サブジャンル": [
        "幻想・怪奇",
        "古典文学"
      ],
      "時代": [
        "古典文学"
      ],
      "文学運動・流派": [],
      "テーマ": [
        "死・生死観",
        "幻想・怪異"
      ],
      "形式・文体": []
    }
  }
}