{
  "contents": {
    "content_0.html": {
      "headings": [],
      "summary": "書き手は、かつての母親たちが娘のために準備した生涯の仕度は、嫁入りの衣装と護身の一振りの懐剣しかなかったと振り返る。これに対し、現代の若い母親たちは、娘への愛情を次世代の女性全体の幸福へと広げ、その精神的支えとして一冊の本を書くという新たな形をとるようになったと述べる。時代の変化の中で、母親の愛が娘個人への守りから、社会全体への寄与へと拡張された様子が描かれている。この展開は、母性の本質が時代とともにどのように変容し、より建設的な形を獲得したかを示すものである。書き手は、そのような変容を「何とよろこばしいことか」と称賛し、一九四〇年十二月に記された心情を込めて締めくくっている。語り手は第三者の視点から、母と娘、そして時代の変遷を俯瞰的に捉え、温かい祝意を込めた筆致でこの部分を終結させている。"
    }
  },
  "overall": {
    "summary": "書き手は、かつての母親たちが娘に授けた仕度が、嫁入りの衣装と護身の一振りの懐剣という、個人への守りだったと振り返る。一方、現代の若い母親たちは、娘への愛情を次世代の女性全体の幸福へと広げ、その精神的支えとして一冊の本を書くという新たな形をとったと記す。この作品は、母性の本質が時代の変遷とともに、狭隘な家内への愛から社会全体への寄与へと大きく拡張し、より建設的な形を獲得した変容を描き出している。書き手は、このような母性の成熟と進化を「何とよろこばしいことか」と称賛し、一九四〇年十二月の心情を込めて終結する。第三者の視点から母と娘、そして時代の流れを俯瞰的に捉えたこの筆致は、温かい祝意に満ちた作品となっている。",
    "tags": {
      "ジャンル": [
        "随筆・エッセイ"
      ],
      "時代": [
        "昭和文学"
      ],
      "文学運動・流派": [],
      "テーマ": [
        "家族・人間関係",
        "女性の生き方",
        "成長・青春"
      ],
      "形式・文体": []
    }
  }
}