{
  "contents": {
    "content_0.html": {
      "headings": [],
      "summary": "湖畔に暮らすギンは、湖畔の女に会うため焼いたパン・生パン・半焼パンを繰り返し持ちかけ、ようやく女性との結婚に成功する。湖畔の老紳士から双子の姉妹の中から正体を見極めるよう命じられ、靴の紐の結び方の違いを察知して正体を選んだギンは、女と共に幸せな生活を送る。しかし、妻は「無実の罪で三度殴られたら湖へ帰る」という条件を課していた。最初の出来事では、妻の馬を手綱で打ってしまい一回目を犯した。続いて、病死する赤ん坊を見て悲嘆する妻を励ますため、悲しみのあまり肩を叩いたことで二回目を犯す。最後は、同じ赤ん坊の死を喜ぶ妻を注意しようとして肩に手をかけたことが、ついに三度目の殴打となり、妻は家畜を連れて湖へ去ってしまう。ギンは妻を求めて湖に身を投げたが、妻は三子を湖から呼び寄せ、薬草の知識を与えて医者に成長させ、その後湖に戻った。"
    }
  },
  "overall": {
    "summary": "湖畔で孤独に暮らすギンが、湖畔の女との結婚という夢を実現するため、試練を経て家畜と共に湖へ去る妻のもとへ身を投じる物語である。男は女に三度の殴打という過酷な条件を課されながら、子殺しという絶望的な状況下で妻子を失い、最後に自ら湖に飛び込み追跡する。しかし、妻は湖から子供たちを呼び寄せ、彼らに医術を授けた上で再び湖へと戻っていった。ギンの行動は、人間の理屈や倫理を超えた「愛」の絶対性と、死生観における神秘の深さを浮き彫りにする。物語は、日常の悲劇がどのように神話的・伝奇的な変容を遂げるかを描き出し、人間の弱さと自然への畏敬の念、そして生死の境界線を越える力強い絆を主題としている。",
    "tags": {
      "ジャンル": [
        "短編小説"
      ],
      "サブジャンル": [
        "幻想・怪奇"
      ],
      "時代": [],
      "文学運動・流派": [],
      "テーマ": [
        "死・生死観",
        "孤独・疎外"
      ],
      "形式・文体": []
    }
  }
}