{
  "contents": {
    "content_0.html": {
      "headings": [],
      "summary": "語り手は、日本へ煙草が伝来した伝説として、フランシス・ザビエルの一行に伴われた悪魔が、誘惑する対象を得られないことへの退屈から、西洋の植物の種を隠し畑に播種し、紫の花を咲かせるまでの経緯を語る。悪魔は、信心深い牛商人と花の名前を当てる賭けを結ぶが、牛商人は悪魔が正体だと気づき、牛を使って畑を荒らさせながら悪魔に「煙草畑を荒らすな」と言わせてしまう。これにより牛商人は契約を破り煙草を入手するものの、語り手は、肉体的・精神的な救いを得た牛商人と引き換えに、悪魔が日本全国に煙草という「悪」を普及させたという皮肉な帰結を指摘する。物語は、悪魔が最終的に日本から去ったが、その後の動静は不明であると記して終わる。"
    }
  },
  "overall": {
    "summary": "語り手は、日本へ煙草が伝来した伝説を、フランシス・ザビエルの一行に伴われた悪魔の視点から語ります。誘惑する対象を得られなかった悪魔は退屈し、西洋の植物の種を隠し畑に播種。やがて紫の花が咲く中、信心深い牛商人と名前を当てる賭けを交わしますが、商人は悪魔の正体を見抜き、牛を使って畑を荒らして契約を破るも、結果的に煙草を入手します。これは肉体的・精神的な救いをもたらしましたが、悪魔が日本全国に「悪」として煙草を普及させた皮肉な帰結でもあります。物語は悪魔が去った後、その動静は不明のまま終了します。本作は、伝説という枠組みを通じて、悪意が人間の生存や欲望に結びつき、結果として社会に浸透する過程を描きます。読者には、神話的な想像力と人間存在の機微が織り成す、風刺と虚無感が混在する独特の情景が提示されます。悪魔と人間の対話から読み解く、善悪の境界線や文明の受容に対する鋭い問いかけが魅力です。",
    "tags": {
      "ジャンル": [
        "短編小説"
      ],
      "サブジャンル": [
        "幻想・怪奇",
        "寓話"
      ],
      "時代": [],
      "文学運動・流派": [],
      "テーマ": [
        "人間の内面・自我",
        "死・生死観",
        "社会批評・風刺"
      ],
      "形式・文体": []
    }
  }
}