{
  "title": "報恩記",
  "original_title": null,
  "author": "芥川龍之介",
  "translator": null,
  "country": "日本",
  "genre": "短編小説",
  "subgenre": [
    "歴史小説",
    "文芸小説"
  ],
  "publication_year": 1922,
  "japanese_publication_year": 1922,
  "summary": "大正11年（1922年）に『中央公論』で発表された芥川龍之介の短編小説です。安土桃山時代の京都を舞台に、盗賊・阿媽港甚内、廻船商人・北条屋弥三右衛門、およびその勘当された息子で隠れキリシタンの弥三郎の三人が、南蛮寺の宣教師の前で真実を吐露します。本作は「恩返し」の本質を三つの視点から描き、一見美徳とされる行為に隠されたエゴイズムや矛盾を浮き彫りにしています。『藪の中』と同様の複数視点構成を採用しながらも、三者の証言が正確に組み合わさる点で異なり、恩義と親孝行の本来的な姿を深く追究した作品です。",
  "themes": [
    "恩返し",
    "親孝行",
    "エゴイズム",
    "真実と欺瞞",
    "罪と救済",
    "キリスト教",
    "人間関係の矛盾"
  ],
  "tags": [
    "歴史小説",
    "複数視点構成",
    "キリシタン",
    "安土桃山時代",
    "恩義",
    "短編",
    "京都",
    "道徳的矛盾",
    "芥川龍之介",
    "大正文学"
  ],
  "awards": [],
  "notable_points": "本作は『藪の中』と同じく複数の登場人物が自らの視点で事件を語る構成を持ちますが、『藪の中』では三者の証言が矛盾するのに対し、『報恩記』では三者の証言が正確に組み合わさることが特徴です。また、盗賊、商人、勘当された息子という三つの立場から「恩返し」という行為の本質を問い直し、一見道徳的とされる行動の背後に隠されたエゴイズムを描いています。あまり論じられることの少ない作品ですが、この三極構成と恩義の相対化に注目できる重要な作品として評価されています。",
  "source_urls": [
    "https://www.aozora.gr.jp/cards/000879/card50.html",
    "https://www.amazon.co.jp/%E5%A0%B1%E6%81%A9%E8%A8%98-%E8%8A%A5%E5%B7%9D-%E7%AB%9C%E4%B9%8B%E4%BB%8B-ebook/dp/B009IWR4Z0",
    "https://ja.wikipedia.org/wiki/%E5%A0%B1%E6%81%A9%E8%A8%98"
  ],
  "book_id": 50,
  "generated_at": "2026-05-09T20:37:42.446520+00:00"
}