{
  "book_id": 916,
  "title": "豚吉とヒョロ子",
  "author": "夢野久作",
  "translator": null,
  "country": "日本",
  "publication_year": 1926,
  "summary": "夢野久作による児童向けの短編作品です。豚吉とヒョロ子という個性的なキャラクターを主人公とした、ユーモアあふれるお話です。本作は『九州日報』の1926年（大正15年）1月～3月に連載されました。夢野久作の得意とする、奇想天外で幻想的な表現手法を用いながらも、児童にも分かりやすい言葉遣いで展開する物語として、日本児童文学における独特の位置づけを持つ作品です。作者が死の約半年前に執筆された大作群の一つとして、その創作活動の幅広さを示すものとなっています。",
  "tags": {
    "ジャンル": [
      "短編小説",
      "童話・児童文学"
    ],
    "時代": [
      "大正文学"
    ],
    "文学運動・流派": [],
    "テーマ": [
      "ユーモア・滑稽"
    ],
    "形式・文体": []
  },
  "source_urls": [
    "https://www.aozora.gr.jp/index_pages/person96.html",
    "https://yozora.main.jp/cgi-bin/inp/kokai.cgi?p=000096"
  ],
  "generated_at": "2026-05-10T00:00:28.083150+00:00"
}