{
  "contents": {
    "content_0.html": {
      "headings": [],
      "summary": "豪放だが愚鈍な青年・朱爾旦は、友人との賭けで十王殿の恐ろしい判官の木像を持ち帰り、その夜に判官（陸）が現れて酒を酌み交わす。陸は朱の鈍い心を賢いものと交換し、その結果朱は才覚を得て科挙に次々と合格するようになる。その後、朱の妻の美しさを惜しんだ陸が、他殺された美女の首を朱の妻に付け替える術を施す。この事件を巡り、被害者の父呉侍御が朱を疑い訴えるが、被害者の亡霊が夢を通じて真犯人を告発したことで事件は解決し、朱は呉の娘婿として迎えられる。しかし朱は礼闈（京試）の規則に抵触して登用されず、官吏への意欲を失う。三十数年後、陸から寿命の終りを告げられた朱は泰然と世を去るが、霊となって妻と子を訪ね、子を教育し、やがて大華卿となり異界の高官になることを語る。最後に、息子・緯が父から授かった佩刀を孫に譲ることで、家系が栄える姿が描かれる。"
    }
  },
  "overall": {
    "summary": "豪放だが愚鈍な青年・朱爾旦が、判官・陸判と交流しその脳天を交換されることで才覚を得るという奇抜な筋から物語は始まる。しかしその代償は重く、彼の妻の首を他人のものと入れ替えるという不気味な事件へと発展し、真実と正義の行方が問われることになる。夢の中での亡霊の告発により真相が解明された後、朱は出世の機会を得るも官吏への意欲を失い、老いを迎えて平静に世を去る。霊となった彼は再び息子に現れ、家系の繁栄を見守り抜く。これは、死と生、そして賢愚の逆転を描く幻想的な物語であり、人間の運命や死生観を怪異の要素を交えつつ風刺的に描く深遠な読み味を持つ。奇想天外な設定の下に潜むのは、功名心への批判と、人間の本質を問う哲学的な思索であり、読者に生と死の境界を思わせる独特の叙情を提示する。",
    "tags": {
      "ジャンル": [
        "短編小説"
      ],
      "サブジャンル": [
        "幻想・怪奇",
        "寓話",
        "ダーク・陰鬱"
      ],
      "時代": [
        "江戸文学"
      ],
      "文学運動・流派": [],
      "テーマ": [
        "死・生死観",
        "知識人の苦悩",
        "哲学・思想",
        "人間の内面・自我",
        "罪・贖罪"
      ],
      "形式・文体": [
        "詩的散文"
      ]
    }
  }
}