{
  "book_id": 223,
  "title": "晩餐",
  "author": "素木しづ",
  "translator": null,
  "country": "日本",
  "publication_year": null,
  "summary": "嵐の夜、狭い部屋で若い夫婦と幼い娘が夕食を共にする情景を描いた作品です。子どもの無邪気な行動に微笑む両親の温かさが印象的ですが、母親が冷たいジャガ芋を口にした瞬間、日々の貧困や疲労の現実へと意識が引き戻されます。結婚後わずか三年の間に経験した苦しみや悲しみが静かに蘇りながらも、母親の心には幻のような安らぎのビジョンが浮かびます。人生の苦難が最終的に懐かしさと許しへと変わる日への深い信念を通じて、家庭の微かな幸福と人生の本質的な救いを瞑想的に描き出す秀作です。",
  "tags": {
    "ジャンル": [
      "短編小説"
    ],
    "時代": [
      "大正文学"
    ],
    "文学運動・流派": [
      "白樺派"
    ],
    "テーマ": [
      "家族・人間関係",
      "心理描写",
      "貧困・社会問題",
      "宗教・信仰"
    ],
    "形式・文体": []
  },
  "source_urls": [
    "https://note.com/ico_bird/n/nea3de007cb3a"
  ],
  "generated_at": "2026-05-09T21:37:17.990810+00:00"
}