{
  "contents": {
    "content_0.html": {
      "headings": [],
      "summary": "案内者によって赤沢の渓谷へ到着した語り手は、岩だらけの荒涼とした峡谷の風景を詳細に描写する。無数の大小さまざまな石が洪水のように谷を埋め尽くし、灰色の岩山と青空が対比する中、案内所となる巨大な岩とその下で火を焚いた痕跡が、自然の圧倒的な力と荒廃を象徴的に示す。その光景に直面し、語り手は自然の厳しさに疲れを感じる。\n\n夜明けを待たずに、中原を先頭とした一行は寒気に凍える谷を攀登を始める。視界がきかない暗闇の中、不安定な石を四つん這いで登り、凍った地面の冷たさを身にしみる。途中、谷底で点滅する白い物体（市村の帽子や中塚の浴衣）の影を視覚化し、遠景には槍ヶ岳や連山が星々と月の光を背景に浮かび上がる。山岳の深い静寂が「死のしずけさ」を呼び起こす中、案内者の声で雷鳥の鋭い鳴き声が聞こえる。語り手は、その冷厳な自然環境と、そこにある神秘性や畏怖の念を内面的に体験しつつ、登山を続ける。"
    }
  },
  "overall": {
    "summary": "案内者の導きにより赤沢の渓谷に辿り着いた語り手は、洪水のように石が堆積する荒涼とした谷と、その中央に聳える巨大な岩の光景を目の当たりにする。灰色の岩山と青空の対比、火を焚いた痕跡などが自然の圧倒的な力と荒廃を象徴し、語り手はそこに自然の厳しさを痛感する。夜明けを待たず、中原ら一行は寒気に凍える谷を四つん這いで攀登を始める。視界を奪う暗闇と不安定な石の上を進む中、谷底に映る白い物体の影や、星々と月明かりに浮かぶ槍ヶ岳の山岳群が幻想的な光景を織り成す。死の静寂を感じさせる深山の空気に、雷鳥の鋭い鳴き声が響き渡る。語り手はこの冷厳な自然環境の中で、畏怖と神秘性を内面的に体験し、人間と自然の対峙を静かに描き出す。",
    "tags": {
      "ジャンル": [
        "短編小説"
      ],
      "サブジャンル": [
        "叙情的"
      ],
      "時代": [
        "昭和文学"
      ],
      "文学運動・流派": [],
      "テーマ": [
        "自然描写",
        "孤独・疎外"
      ],
      "形式・文体": []
    }
  }
}