{
  "contents": {
    "content_0.html": {
      "headings": [],
      "summary": "語り手は、芸術作品がもたらす真の慰安の源について思索を深める。浅い楽観主義や作家の気質に留まらない、人間苦や悲しみの中から響き上がる複雑な音楽性が、逆に精神をよろこびの感覚へと高めるという逆説を説く。次に、アランの『文学語録』における「散文は調整を求める受動的なものであるが、詩は自己均衡の能動的な表現である」という見解を紹介する。しかし語り手は、散文が単に外的力への反応に終始するのではなく、創作過程を通じて人間が救済された状態を内在させ、新しい人生の価値を構築するものだと反論する。アランの二分法に拘泥することは、現代の散文精神が屈伏し、美が喪われている要因となっていると指摘し、芸術の言葉としての散文の可能性を再考する。一九四〇年二月の時点における、文学論的・美学的な深い洞察と痛烈な批判が展開されている。"
    }
  },
  "overall": {
    "summary": "この作品は、芸術作品、特に散文が人間にもたらす真の慰安の源について思索を深める文学論的エッセイである。語り手は、浅い楽観主義や単なる作家の気質を超え、人間苦や悲しみの中から響き上がる複雑な音楽性が、逆説的に精神を喜びへと高めうることを説く。また、アランの「散文は受動的、詩は能動的」という二分法を紹介しつつ、それにとどまらず、散文こそが創作過程を通じて救済された状態を内在させ、新しい人生の価値を構築する能動的な表現であると反論する。アランの枠組みに固執することが現代の散文精神の屈伏や美の喪失を招くと指摘し、一九四〇年二月という時代の深淵において、文学論的かつ美学的に痛烈な批判と再評価が展開される。苦悩と美の辩证法的関係を描く、極めて知的で詩情に富む作品である。",
    "tags": {
      "ジャンル": [
        "随筆・エッセイ"
      ],
      "時代": [
        "昭和文学"
      ],
      "文学運動・流派": [],
      "テーマ": [
        "人間の内面・自我",
        "芸術・創作論"
      ],
      "形式・文体": [
        "詩的散文"
      ]
    }
  }
}