{
  "contents": {
    "content_0.html": {
      "headings": [],
      "summary": "主人公のしゅん子は、妊娠中のお嫂にスルメを届けようとしたが、雪道を歩いているうちにそれを落としてしまう。落胆する彼女だったが、兄の「人間の眼には風景が定着する」という嘘めいた話と、デンマークの伝説を思い出し、雪の美しい夜景を記憶することで新たな土産にしようと決意する。帰宅後、その約束の眼を開いてお嫂に見せようとするが、その瞬間に兄が現れ、「山形の壮麗な雪景色を二十年見てきた私の眼の方が優れている」と主張し、主人公を侮辱する。兄の過剰な自信と自意識過剰な振る舞いに憤る主人公に対し、お嫂は冷静に「兄の眼は美しいものだけでなく、汚いものも同様に多く見てきたために黄色く濁っている」と指摘し、兄を黙らせる。この一場面で、主人公の純粋な美への希求と、兄の歪んだ誇り、そして温かい家族の絆が対比され、物語に新たな深みが加わる。語り手は主人公の一人称視点で、心情の移ろいと家族関係の変化を内面的に描いている。"
    }
  },
  "overall": {
    "summary": "妊娠中のお嫂にスルメを届ける途上で落としてしまったしゅん子が、雪の夜景を記憶して新たな土産にしようと心に決める物語。しかし、帰宅した兄が「二十年見た自分の眼の方が優れている」と主張し、主人公を侮辱する場面から緊張が高まる。そこでお嫂が「兄の眼は美しいものだけでなく汚いものも見たために黄色く濁っている」と指摘し、兄を黙らせるという構成だ。純粋な美への希求と、歪んだ誇り、温かい家族の絆が対比され、人間関係の機微が浮き彫りになる。一人称視点による心情の移ろいを通じて、美しさをどう捉え、誰と共有するかという問いが描かれる。雪景色の美しさと、人間のエゴや老いた目線の対比が印象的で、静かなる内省と温かい共感が作品を支配する叙情的な読み味である。",
    "tags": {
      "ジャンル": [
        "短編小説"
      ],
      "サブジャンル": [
        "叙情的"
      ],
      "時代": [
        "昭和文学"
      ],
      "文学運動・流派": [],
      "テーマ": [
        "人間の内面・自我",
        "家族・人間関係"
      ],
      "形式・文体": [
        "独白体"
      ]
    }
  }
}