{
  "title": "まざあ・ぐうす",
  "original_title": "Mother Goose",
  "author": "不詳",
  "translator": "北原白秋",
  "country": "イギリス",
  "genre": "児童文学",
  "subgenre": [
    "童謡",
    "童謡集",
    "翻訳作品"
  ],
  "publication_year": null,
  "japanese_publication_year": 1930,
  "summary": "イギリスの伝統的な童謡集『マザー・グース』を日本語に翻訳した作品です。北原白秋による翻訳版として、アルス社から昭和5年に出版されました。赤い鳥などの児童文学雑誌に掲載された翻訳をまとめたもので、マザー・グースのナンセンスで楽しい世界観を日本の読者に紹介しています。子どもたちのための韻文的な物語や言葉遊びが特徴で、英語圏の子どもたちに親しまれてきた作品群を日本語で表現した翻訳児童文学の代表的なものです。",
  "tags": [
    "児童文学",
    "童謡",
    "翻訳作品",
    "イギリス文学",
    "北原白秋"
  ],
  "source_urls": [
    "https://www.aozora.gr.jp/cards/001529/files/546_21324.html",
    "https://www.aozora.gr.jp/cards/001529/card546.html"
  ],
  "book_id": 546,
  "generated_at": "2026-05-09T23:15:53.630532+00:00"
}