{
  "contents": {
    "content_0.html": {
      "headings": [],
      "summary": "語り手は東日本大震災後の社会と人心を、易経の「震」卦にある「恐懼修省」の教えに照らしつつ論じる。震災以前、人々は自らの知恵や規模を過信し、慢心と侮りが社会を支配していた。しかし、自然の恐怖の前にその傲慢さが無力であることを悟らされた今こそ、恐れを以て自らを慎み、内面を修めることが救済への道であると説く。慢心を捨てて粛然とした態度へと転じるなら、再び悲惨な結末を迎えることはない。また、地震学は未だ幼い科学であり、予知ができなかったや測定器の性能が未熟だったと非難するのは道理に反する。子供を愛護するように科学を育て、理解し尊敬すべきであると訴える。さらに、震災前に流行った悲しい童謡などを過去の歴史的な事例と照らして考察し、人々が事後に記憶を操作し、当時の不安を「前兆」と誤解する心理の仕組みを指摘する。最終的に、社会の風習や歌謡を重視し、治める者はその変化に留意するべきであるとする。"
    }
  },
  "overall": {
    "summary": "語り手は東日本大震災後の社会を「恐惧修省」の視座から紐解く。震災以前、人々は知恵と規模を過信する慢心に陥り、自然の脅威を侮っていた。しかし、巨大地震の衝撃はその傲慢さを無力と突きつけ、科学的な予知の不備を非難する風潮こそが道理に反すると断じ、科学を幼子の如く愛護し育てるべきであると訴える。また、過去の悲しい歌謡や社会の風習が、人々の記憶操作によって「前兆」と誤解される心理的メカニズムを指摘し、震災を機に人々が内面を慎み、恐怖を糧として真の救済へと至る道程を描く。作品は自然と人間の関係、科学への態度、集団心理の変容を深く掘り下げつつ、人間の内面における自省の重要性を力強く問いかける。読みどころは、易経の古典的な知恵と現代の科学技術を対比させる独特な視点と、震災という悲劇を通じて社会がどうあるべきかを論じた哲学的な洞察である。自然災害という外在的な危機に対し、内面からの転回こそが人類の未来を救うという主張は、読者に深い思索を促す。",
    "tags": {
      "ジャンル": [
        "散文詩"
      ],
      "時代": [
        "戦後文学"
      ],
      "文学運動・流派": [],
      "テーマ": [
        "哲学・思想",
        "人間の内面・自我",
        "自然描写"
      ],
      "形式・文体": []
    }
  }
}