{
  "contents": {
    "content_0.html": {
      "headings": [],
      "summary": "語り手（作者）は、胎内より貧乏を予感して出生したことに始まり、八畳半の狭小住宅で父が古着商として五十年間奮闘してきた貧窮の家庭で育ったと回想する。弟の出世を優先せざるを得ない状況でも、自身には学費を援助され、秀才として扱われた。父への恩義と貧乏へのひがみから、彼もまた同様の生き方を強いられる。その後、作者は結婚・出産により経済的に破綻し、妻を雇って家計を維持しながら極限の貧困を味わう。就職試験で失敗し、絶望の中にあったが、同僚の紹介で翻訳仕事を得て一時的に立ち直る。その後も出版社の設立や高利貸しとの交渉、関東大震災による避難、菊池寛からの救済金による涙の経験など、波乱に満ちた生活が続く。それでも「文士家業」の寿命を悟りつつ、貧乏こそが根気と楽観性を生むと捉え、絶望的な状況でも筆を折らずに勉強と創作に打ち込む決意を示し、貧窮の人生を肯定する。語り手は一人称であり、初期の胎内からの視点から、中年期の回顧と現在への展望へと時間軸が流れる。"
    }
  },
  "overall": {
    "summary": "語り手は胎内より貧乏を予感して生まれ、父が古着商として奮闘する狭小な家庭で育つ。弟の出世を優先される中、自身は学費を援助され秀才として扱われるも、父への恩義と貧乏へのひがみから同じ道を歩むことを強いられる。結婚・出産による経済破綻や極限の貧困、就職試験の失敗、関東大震災などの波乱を乗り越えつつも、筆を折らずに創作を続ける。その中で、貧窮こそが根気と楽観性を生むものとして肯定し、文士としての使命を全うする決意を示す。一人称の視点で胎内からの回想から中年期の回顧へと時間軸が流れ、苦難の人生を内省的に描き出す。本作は、貧困という現実と向き合い、そこから精神的な強さを見出す人間の姿を描いた作品である。自己の境遇を内省的に分析し、苦難を糧とする姿勢は読者に深い思索を促す。文学的価値は、貧窮という素材を芸術的に昇華し、人間の忍耐と希望の物語として語る点にある。",
    "tags": {
      "ジャンル": [
        "短編小説"
      ],
      "サブジャンル": [
        "叙情的",
        "哲学的・思索的"
      ],
      "時代": [
        "昭和文学"
      ],
      "文学運動・流派": [],
      "テーマ": [
        "人間の内面・自我",
        "貧困・社会問題",
        "死・生死観"
      ],
      "形式・文体": [
        "独白体"
      ]
    }
  }
}