{
  "contents": {
    "content_0.html": {
      "headings": [],
      "summary": "1935 年 1 月、女流作家が男の作家による女性描写について議論する対談の続く部分。語り手（答）は、優れた男作家たちも多くの女性像を描いているが、依然として「男にとって都合のよい女性」に限られており、女自身の葛藤や社会生活における真の要求が十分表現されていないと指摘する。日本の封建的社会構造の中で女性が抑圧される現実や、経済的合理性のために結婚相手を選ぶような複雑な女性の実像が、男作家の伝統的な視点では捉えきれていないとする。菊池寛や谷崎潤一郎の作品を例に挙げつつ、彼らが描く女性には社会的・歴史的前進を捉えた「新しい文学における女の内容」の欠如があると論じる。語り手は、新しい女性像を記述するには、従来の既成概念にとらわれず、男にとって都合の悪い感情や行動さえも客観的・批判的に描き出せる、プロレタリア文学的な「新しい社会観」を持った作家の登場を期待し、それが現代文学の課題であると結ぶ。"
    }
  },
  "overall": {
    "summary": "本作品は、1935 年 1 月に行われた女流作家と男作家による対談の抜粋である。語り手は、優れた男作家たちが数多くの女性像を描いてきたにもかかわらず、なおも「男にとって都合のよい女性」に留まり、女性自身の葛藤や社会生活における真の要求が表現されていないと指摘する。封建的社会構造による抑圧や、経済的合理性に基づいた結婚選択など、女性の実像は男の伝統的視点では捉えきれていないとするものである。菊池寛や谷崎潤一郎らの作品を例に挙げ、そこには社会史的視点に立った「新しい女性像」の欠如があると論じる。語り手は、既成概念にとらわれず、男にとって不都合な感情さえも客観的・批判的に描き出せる、プロレタリア文学的な新社会観を持つ作家の登場を期待し、それが現代文学に残された重要な課題であると結んでいる。これは当時の文壇における性差別的な視線への鋭い批判であり、女性文学の在り方を深く思索させる内容である。",
    "tags": {
      "ジャンル": [
        "散文詩"
      ],
      "サブジャンル": [
        "哲理的"
      ],
      "時代": [
        "昭和文学"
      ],
      "文学運動・流派": [
        "プロレタリア文学"
      ],
      "テーマ": [
        "女性の生き方",
        "社会批評・風刺",
        "人間の内面・自我"
      ],
      "形式・文体": [
        "独白体"
      ]
    }
  }
}