{
  "contents": {
    "content_0.html": {
      "headings": [],
      "summary": "二月に学位辞退を申し出ていた語り手（夏目漱石）は、四月上旬に上田万年と芳賀矢一の好意的仲介により、福原専門学務局長と対話する。文部省は辞退を撤回し学位を授与しようとするが、語り手はこれを拒絶し、文部大臣が自らの意思を無視して学位辞退を認めない点に強い不満を抱く。四月十三日、語り手は局長宛てに正式な文書を提出し、文部省の意向に従わぬ限り学位を受ける義務はないと明確に声明する。これは単なる個人的な争いではなく、博士制度が学問を貴族化し弊害を招く現状への深い憂慮に基づく、確固たる主義の表明である。語り手は世間の常識に左右されることなく、自らの判断を貫く自由を主張し、この問題は双方が譲歩しない限り解決しない沈黙の継続へと向かうことが描かれる。一貫して「余」という一人称視点で語られ、語り手の内面と思想的背景が直接語られる構成である。"
    }
  },
  "overall": {
    "summary": "語り手である夏目漱石が、学位辞退の件を巡って文部省と対立する様子が描かれる。二月に辞退を申し出ていた彼だが、上田万年らによる仲介で局長と対話するも、文部省の強硬な撤回圧力に対し、博士制度が学問を貴族化し弊害を招くという根本的な懸念から、沈黙をもって拒絶を続ける。これは個人的な名誉をかけた争いではなく、学問の独立と真摯な姿勢を守るための思想的な決断である。語り手は「余」という一人称で自らの内面と思想を率直に告白し、世間の常識に屈せず、自らの判断を貫く自由を主張する。双方が譲歩しないまま続く対立の中で、個人の良心と制度の矛盾が浮き彫りにされる。この作品は、知識人が社会的権威と向き合う際の葛藤と、真理への誠実な姿勢を鮮明に描き出した傑作である。",
    "tags": {
      "ジャンル": [
        "短編小説"
      ],
      "サブジャンル": [
        "哲学的・思索的"
      ],
      "時代": [
        "明治文学"
      ],
      "文学運動・流派": [
        "新思潮派"
      ],
      "テーマ": [
        "人間の内面・自我",
        "知識人の苦悩",
        "哲学・思想"
      ],
      "形式・文体": [
        "独白体"
      ]
    }
  }
}