{
  "book_id": 1067,
  "title": "人外魔境",
  "author": "小栗虫太郎",
  "translator": null,
  "country": "日本",
  "publication_year": 1968,
  "summary": "世界的に有名な日本人探検家・折竹孫七の冒険譚を、小説家の「私」が聞き書きしてまとめた連作短編シリーズです。1939年から1941年にかけて雑誌『新青年』に掲載された全13話を、1968年に初めて一冊にまとめた作品です。アフリカ、太平洋、アジアなど世界各地の未踏の魔境を舞台に、奇想天外な冒険が繰り広げられます。折竹は理学士でありながら日本のスパイでもあり、科学的知識と愛国心を持って危険な秘境に挑み続けます。エドガー・ライス・バローズやジュール・ヴェルヌらの冒険小説の影響を受けながら、著者独自の想像力で創造された奇想天外な世界が特徴です。",
  "tags": {
    "ジャンル": [
      "短編小説",
      "連作短編",
      "冒険・活劇",
      "SF・科学小説"
    ],
    "時代": [
      "昭和文学"
    ],
    "文学運動・流派": [],
    "テーマ": [
      "冒険・活劇",
      "知識人の苦悩"
    ],
    "形式・文体": [
      "連作短編"
    ]
  },
  "source_urls": [
    "https://www.aozora.gr.jp/cards/000125/card1320.html",
    "https://ja.wikipedia.org/wiki/%E4%BA%BA%E5%A4%96%E9%AD%94%E5%A2%83",
    "https://bookmeter.com/books/472191"
  ],
  "generated_at": "2026-05-10T00:12:29.418835+00:00"
}