{
  "contents": {
    "content_0.html": {
      "headings": [],
      "summary": "消防の副小頭・植峰峰吉と、元酌婦のお八重の夫婦生活を描く。茂助という孤児が養子として暮らす中、お八重の妊娠を巡り茂助との不倫疑惑が町で広まる。峰吉は疑心暗鬼ながらも、お八重に「自分の子」としての安心感を与えようとし、茂助にも無関心でいる。しかし、その晩、茂助がお八重に「子供は峰吉の子」と言い、峰吉の存在を強調する芝居を打つ直後、峰吉は突然姿を消す。翌朝、隣接する湯屋が放火され、茂助と番台の娘が焼死した。茂助は「湯屋を助け殉職した英雄」として町葬が行われるが、お八重は茂助の死が峰吉による殺人、すなわち不倫の真相を知り隠蔽し、峰吉が茂助を突き落としたと告発する。夫を責めるお八重に対し、峰吉は激しい感情の波を隠せず、表彰文を読み上げる場面が滑稽さと悲劇性を帯びて結ばれる。語り手は第三人称で、人物の心理と風刺を客観かつ痛烈に描き、峰吉の内面や茂助の無自覚な性格を浮き彫りにする。"
    }
  },
  "overall": {
    "summary": "消防の副小頭・植峰峰吉と元酌婦・お八重の夫婦生活が描かれる。不倫疑惑を巡り、孤児の茂助が峰吉の存在を強調する芝居を打った直後、峰吉は突然姿を消す。翌朝、湯屋が放火され茂助が焼死するも、お八重は真相を隠蔽し夫を告発。しかし峰吉の動揺や、表彰文を読み上げる場面の滑稽さの中で、夫の心情が浮き彫りとなり、悲劇と風刺が交錯する形で結ばれる。この作品は、不道徳な行為への罪悪感や、社会的な評価と内面の葛藤という人間の内面を鋭く抉る。主人公の峰吉が、他人からの偏見や自己の罪悪感に翻弄される様子は、心理描写の深さと風刺的な効きを際立たせている。特に、町民の反応と峰吉の狂信的なまでの潔白への執着が対比される演出は、人間社会の愚かさと虚構を痛烈に描き出しており、読み手を戦慄と苦笑に陥らせる。",
    "tags": {
      "ジャンル": [
        "短編小説"
      ],
      "サブジャンル": [
        "推理・探偵",
        "ダーク・陰鬱"
      ],
      "時代": [
        "明治文学"
      ],
      "文学運動・流派": [
        "新思潮派"
      ],
      "テーマ": [
        "心理描写",
        "人間の内面・自我",
        "罪・贖罪",
        "社会批評・風刺"
      ],
      "形式・文体": [
        "心理描写"
      ]
    }
  }
}