{
  "contents": {
    "content_0.html": {
      "headings": [],
      "summary": "西蔵チベットの屋頂エベレストを舞台にした寓言小説の一部である。悪知恵に長け、他鳥を騙して捕食する鴉のラランは、頂上を目指すが一人では達成できず、純粋な若鴉のペンペを味方に引き込む。ラランはペンペに自分自身の眼玉を食らうよう嘘をつき、ペンペは二回にわたり両眼を抉り取って盲目になる。ラランはこれを機に単独飛行で頂上へ向かい、最終的にエベレストの怒りに触れ、氷塊の襲撃を受けて墜落する一方、盲目のまま霧の中で彷徨い墜死したペンペの遺体は、下界の旅行者たちによって発見される。物語はラランの堕落と傲慢さによる破滅、そして被害者の悲劇を通じて、悪が招く因果の厳しさを描いている。語り手は全知の視点で物語を進行し、擬人化された登場人物の心理描写と、神聖な山岳における人間性（または動物性）の葛藤を浮き彫りにしている。"
    }
  },
  "overall": {
    "summary": "エベレストを舞台にしたこの物語は、狡知に長けた鴉のラランが、純朴な若鴉のペンペを利用して頂上への挑戦に臨む寓話である。ラランはペンペに対し、自分の眼玉を食らうよう欺き、盲目にさせたペンペの視力を奪って単独で飛行を試みる。その結果、頂上の怒りに触れて墜落し破滅する一方、盲目のまま霧の中で彷徨い亡くなったペンペの遺体は、後に下界の旅行者によって発見される。物語は全知の視点から、ラランの堕落と傲慢さが招いた破滅、そして被害を被ったペンペの悲劇を静謐かつ冷徹に描き出す。自然の厳粛さの中で繰り広げられる動物たちの葛藤は、人間社会における欲望と倫理の逆転を象徴的に示しており、悪行に対する因果応報の厳しさを浮き彫りにしている。幻想的な設定と哲学的な問いかけが交差する叙情的な筆致は、読者に深い内省を迫る。",
    "tags": {
      "ジャンル": [
        "短編小説"
      ],
      "サブジャンル": [
        "寓話",
        "幻想・怪奇"
      ],
      "時代": [],
      "文学運動・流派": [],
      "テーマ": [
        "孤独・疎外",
        "死・生死観",
        "哲学・思想"
      ],
      "形式・文体": [
        "詩的散文"
      ]
    }
  }
}