{
  "contents": {
    "content_0.html": {
      "headings": [],
      "summary": "水が出ない発動機に手を焼く父と、糖尿病で癇癪を起こしやすい母。別荘を訪ねた娘たち（佐和子、晴子）は、家事を手伝う使用人みわの姿から三十年という歳月と変化に寂しさを覚える。父は発動機修理のために旅先から戻り、水の問題を解決すべく電話をかけるが、その夜は子供たちと外へ出る。佐和子と晴子は、母の気遣いで浜辺で待つ父のもとへ駆け寄り、一緒に夕暮れの海岸を歩くことになる。道中、一匹の斑犬が付きまとうが、犬が苦手な父は狂犬ではないかと警戒して駆除しようと必死になり、娘たちはその様子を笑いながらも父の臆病さと孤独な老人としての哀れさを感じ取る。父が犬を追い払おうとして転び、犬が晴子に舐め付けた際、父が激しく嫌悪を示す姿に、佐和子は長年一緒に暮していないために父親との距離感ができたことへの切ない哀愁を深める。二人の娘は、悲しみを抱えつつも、家路につく。"
    }
  },
  "overall": {
    "summary": "糖尿病を患い癇癪を起こしやすい母親と、水が出ない発動機に悩む父親のもとへ、娘の佐和子と晴子が別荘を訪ねる。三十年の歳月が過ぎ、使用人の姿に寂しさを覚える娘たちだが、家計の苦しい中、父親が努力を続ける姿や、娘たちの温かい気遣いの中に、日常の重なり合う悲しみと温かさが描かれる。特に印象的なのは、夕暮れの海岸を歩く父と娘たちの風景だ。犬が苦手な父が斑犬に怯え、その様子から娘たちは、かつての頼れる父親の姿が、孤独な老人としての哀れさを帯びて見えるようになったことに気づく。父が転び犬に接触した際、父が示す激しい嫌悪と、娘たちがそれを受け止める切なさ。これは単なる家族の再会ではなく、時と共に変容していく親子の関係性と、それでもなお続く家族の絆の繊細な機微を捉えた作品である。宮本百合子の筆致は静謐でありながら、人間の弱さや孤独を深く捉え、読者の心に静かな余韻を残す。",
    "tags": {
      "ジャンル": [
        "短編小説"
      ],
      "時代": [
        "昭和文学"
      ],
      "文学運動・流派": [
        "プロレタリア文学"
      ],
      "テーマ": [
        "家族・人間関係",
        "孤独・疎外",
        "心理描写",
        "貧困・社会問題"
      ],
      "形式・文体": [
        "詩的散文"
      ]
    }
  }
}