{
  "contents": {
    "content_0.html": {
      "headings": [],
      "summary": "九月中旬、堅吉の元に差出人不明の球根の小包が届く。里芋に似て細長い球根には帽子のような被りが付いており、家族誰も正体を特定できず、堅吉は過去の類似体験や自身の病状と結びつけて思考を深める。彼は病的なまでに敏感になり、周囲の人間関係や世間の目を極度に過敏に察知し、孤独な思索の海に没入する中、球根を「フリージア」と特定する。その後、実際には疎遠な甥からの発送であったことが判明するも、筆跡の類似性など新たな謎が残る。この出来事をきっかけに、堅吉の内面世界と外側世界の隔絶、そして自己の内なる真理を信じる感と、外部との接触に対する不安との間で揺れる精神状態が浮き彫りとなる。語り手は堅吉の視点（三人称制限）に固定され、その知性、病的な感受性、そして閉鎖的な思考の循環を詳細に描写し続ける。"
    }
  },
  "overall": {
    "summary": "九月中旬、主人公の堅吉のもとに差出人不明の球根が送られてくる。里芋に似たその物体は彼にして見当もつかず、堅吉は自身の病的な感受性や過去の記憶と結びつけて深く思索を巡らせる。周囲の視線を過度に恐れ、孤独な内省の世界に没入する中、ついにその正体がフリージアであると見極める。後にそれが疎遠な甥からの贈り物であったことが判明するものの、筆跡など新たな謎は残る。この出来事は、堅吉の内面世界と外部現実の絶望的な隔絶、そして自己の真理を信じることへの渇望と、他者との接触への恐怖の間で揺れる彼の精神状態を浮き彫りにする。三人称制限視点で描かれるこの物語は、主人公の鋭く病んだ知性と、閉鎖的な思考が循環する世界を繊細に描き出し、孤独と疎外感を漂わせる叙情的な味わいを持っている。",
    "tags": {
      "ジャンル": [
        "中編小説"
      ],
      "サブジャンル": [
        "心理描写"
      ],
      "時代": [],
      "文学運動・流派": [],
      "テーマ": [
        "人間の内面・自我",
        "孤独・疎外",
        "心理描写"
      ],
      "形式・文体": [
        "独白体"
      ]
    }
  }
}