{
  "book_id": 766,
  "title": "コンラッドの描きたる自然について",
  "author": "夏目漱石",
  "translator": null,
  "country": "日本",
  "publication_year": null,
  "summary": "本作は、夏目漱石がイギリスの作家ジョセフ・コンラッドの作品における自然描写について論じた文芸評論です。漱石は、コンラッドが自らの作品の中で自然をいかに描き出しているかを分析し、その特徴と意義を考察しています。西洋文学、特にコンラッドの創作手法に関心を持つ漱石の文学的視点が顕著に表れた作品で、当時の日本における西洋文学受容の重要な記録となっています。文芸評論としての学術的価値と、漱石自身の創作姿勢を理解する上での重要な参考資料です。",
  "tags": {
    "ジャンル": [
      "評論・批評"
    ],
    "時代": [
      "明治文学"
    ],
    "文学運動・流派": [],
    "テーマ": [
      "芸術・創作論",
      "自然描写"
    ],
    "形式・文体": []
  },
  "source_urls": [
    "https://www.aozora.gr.jp/index_pages/person148.html",
    "https://www.satokazzz.com/books/author/148.html",
    "https://archive.org/details/aozorabunko_00766"
  ],
  "generated_at": "2026-05-09T23:41:44.774625+00:00"
}