{
  "contents": {
    "content_0.html": {
      "headings": [],
      "summary": "語り手は源頼義の長男・八幡太郎義家を中心に、その生涯を伝説的エピソードとして語る。義家は幼少より神がかり的な弓の名人であり、奥州安倍氏の戦いでは敵将・貞任との一騎討ちで命を助け、その優しさと度量の広さを示した。凱旋後、許された貞任の復讐心を義家の無二の誠意で改心させると、学問の欠如を指摘されても素直に兵学を学び、後にその知見で伏兵を察知して危機を救う。さらに、都の魔除けや不気味な蛇入りの瓜の正体解明、キツネを射止める技など、常人を超えた武勇と知略が描かれる。義家は七十歳近くまで天皇に仕え、その数多くの逸話后世の武士の模範となった。物語は全編を通じて、語り手による義家の英雄としての絶対的な評価と敬意の念一貫して進行し、視点に揺れはない。"
    }
  },
  "overall": {
    "summary": "本書は、源頼義の長男・八幡太郎義家を中心に、その生涯を伝説的なエピソードとして語る物語である。語り手は、義家が幼少より神がかり的な弓の名手であったことから始まり、奥州征伐において宿敵・安倍貞任との一騎討ちで生死を分ける中、その武勇だけでなく人としての優しさと度量の広さを描き出す。敵対していた貞任を改心させ、学問の不足を指摘されても素直に学ぶ姿など、単なる戦いの英雄を超えた人格が描かれる。また、都での魔除けや不思議な現象の解明など、常人を超えた知略も示される。七十歳近くまで天皇に仕え続けたその生涯は、数々の逸話を通じて後世に武士の理想像として語り継がれる。全編を通じて語り手の義家に対する絶対的な敬意が貫かれ、英雄の本質とは何かを問う作品となっている。",
    "tags": {
      "ジャンル": [
        "歴史小説"
      ],
      "時代": [
        "昭和文学"
      ],
      "文学運動・流派": [],
      "テーマ": [
        "人間の内面・自我",
        "道徳・倫理",
        "冒険・活劇"
      ],
      "形式・文体": []
    }
  }
}