{
  "contents": {
    "content_0.html": {
      "headings": [],
      "summary": "本書は、1933年3月に書かれた文章であり、日本のプロレタリア文学運動において類希な傑出者として描かれる小林多喜二の文学的・人的評価を論じる。小林が小樽時代から勤労階級の苦痛と社会的原因を告発する作品を生み出し、1928年の三・一五事件を題材にした「一九二八年三月十五日」で作家としての方向を確立し、「蟹工船」など精力的な創作活動を通じプロレタリアートの課題を具現化し続けた過程が語られる。著者は、小林の作品中に駄作は殆どなく、その欠点が「作家主義」や日和見主義によるものではなく、新たな闘争の具体性を導入する雄渾な意志から生じたものであると擁護する。また、非合法生活を送りながら理論家・指導者として成長し、最後には「地区の人々」を発表した点を取り上げる。この作品に対し、宮島新三郎が概念的だと批判する一方、著者は完成されていないながらも真に腰の据わった主題性と、次の傑作への道を示す新たな発展段階であると評価し、小林の英雄的殉難と文学的遺産を讃えている。語り手は一貫して小林を敬愛する批評家としての視点から、彼の実践と作品の意義を断固として擁護する。"
    }
  },
  "overall": {
    "summary": "本作品は、1933年に発表された小林多喜二の文学と人生を論じた評論である。著者は、小樽時代から労働階級の苦痛を告発し、三・一五事件を題材にした「一九二八年三月十五日」で作家としての確固たる方向性を確立した小林を、日本プロレタリア文学運動における類稀な傑出者として位置づける。「蟹工船」などの作品群を通じて、新たな闘争の具体性を導入する雄渾な意志が示されると評し、宮島新三郎らが批判する「概念的」という点についても、完成されていないが真に腰の据わった主題性と、次の傑作への道を示す発展段階であると擁護する。非合法生活を営みながら理論家・指導者として成長し、最期には「地区の人々」を残して殉職した小林の英雄的姿と、その文学的遺産の重みを、敬意に満ちた批評家の視点から断固として讃えた力作である。",
    "tags": {
      "ジャンル": [
        "評論・批評"
      ],
      "サブジャンル": [],
      "時代": [
        "昭和文学"
      ],
      "文学運動・流派": [
        "プロレタリア文学"
      ],
      "テーマ": [
        "知識人の苦悩",
        "社会批評・風刺",
        "死・生死観"
      ],
      "形式・文体": []
    }
  }
}