{
  "contents": {
    "content_0.html": {
      "headings": [],
      "summary": "少女（お縫）は夏休みの初日、部屋で小説に没頭するも、翌朝に月経による身体の変化と羞恥心、そして罪悪感に苛まれる。家族に拒絶される恐怖から自室に引きこもり、性別への自虐や男性への憧憬に苦しむ。しかし、兄や友人らとの交流の中で不安を抱えたままも、次第に身体が新たな力に目覚め、心も軽やかになる。その後、姉の病状の重さを知り、死を予感する悲しみに打ちひしがれつつも、兄とのボール遊びで一瞬の喜びを取り戻す。最後に伯母との対面で「大人になった」と称賛され、自身の内面の変化に気づく。語り手は少女の内面心理に密着した視点で、羞恥から受容への感情の起伏と成長の瞬間を描き出している。"
    }
  },
  "overall": {
    "summary": "夏休みの初日、小説に没頭していた少女・お縫は、翌朝の月経をきっかけに羞恥心と罪悪感、そして性別への自虐的葛藤に苛まれる。家族に拒絶される恐怖から部屋に引きこもる彼女だったが、兄や友人との交流、姉の病状の深刻化への悲しみ、そして伯母からの「大人になった」という称賛を契機に、次第に身体と心の新たな変化を受け入れていく。この作品は、少女の生理的変化に伴う苦悩と、そこから萌芽する自我の目覚めを描く成長物語である。羞恥から受容へと至る繊細な感情の起伏を、少女の内面に密着した視点で描き出すことで、青春の転換期における孤独と希望の機微を捉えている。読者は、主人公の心理描写を通じて、誰しもが通る「成長の痛み」と「自立の喜び」を共感的に体験できる。",
    "tags": {
      "ジャンル": [
        "短編小説"
      ],
      "時代": [
        "昭和文学"
      ],
      "文学運動・流派": [],
      "テーマ": [
        "心理描写",
        "孤独・疎外",
        "成長・青春",
        "女性の実の生き方",
        "自然描写"
      ],
      "形式・文体": [
        "詩的散文"
      ]
    }
  }
}