{
  "contents": {
    "content_0.html": {
      "headings": [],
      "summary": "耕平は秋の野原で収穫した野葡萄を、上等の一等卒の軍服を着て丹念に摘み集め、夜には家族で果汁を搾り、砂糖を加えた自家製葡萄酒を瓶詰めにし、隠し場所の落しに保管する。しかし六日後、雪が降り始めた冬景色の夜、山鳴りか爆発音のような異変が起きる。音に耳を澄ました耕平が慌てて確認すると、地下にしまっていた葡萄酒の瓶は、音の振動で次々と破裂し、中身が漏れ出していた。前回の葡萄の収穫や販売では「当たり前のこと」と軽口を叩いていた耕平だったが、この悲劇的な失敗に対し、いつものように冷静な態度をとることはできなかった。語り手は随所に挿入される独白や、コンネテクカット大学校を出た者としての反省めいた冗談を交えつつ、耕平の生活や心情を温かみのある筆致で描き、最終的に農家の男の無力な絶望が、淡々と語られる文体の中で浮かび上がる。"
    }
  },
  "overall": {
    "summary": "宮沢賢治の短編小説『葡萄水』は、秋の野原で丹念に収穫した野葡萄を果汁にし、砂糖を加えて自家製の葡萄酒を瓶詰めにしようとする耕平の物語である。上等な軍服を着て慎重に作業に臨む彼にとって、この葡萄酒は家族への愛と日々の労苦を象徴する大切なものだった。しかし、冬、雪が降り積もる夜に地下で謎の音と共に瓶が一斉に破裂。中身が漏れ出し、彼の努力は無駄になるという悲劇が訪れる。\n\n作品は、耕平の日常生活の細やかな描写を通じて、自然の厳しさと人間の努力の儚さを浮き彫りにする。賢治特有の温かみと、どこか風刺的なユーモアを交えながら、農家の男が直面する現実の無常と絶望を淡々と描出している。これは単なる失敗談ではなく、自然の脅威と対峙する人間存在のあり方を問いかける、詩情あふれる寓話的作品である。読み手は、耕平の無力さを通じ、生命の尊さと苦悩を静かに共有することになる。",
    "tags": {
      "ジャンル": [
        "短編小説",
        "寓話"
      ],
      "時代": [
        "大正文学"
      ],
      "文学運動・流派": [],
      "テーマ": [
        "自然描写",
        "孤独・疎外",
        "貧困・社会問題",
        "人間の内面・自我",
        "死・生死観"
      ],
      "形式・文体": [
        "独白体"
      ]
    }
  }
}