{
  "contents": {
    "content_0.html": {
      "headings": [],
      "summary": "一九三七年三月、語り手は現代日本文学における古典摂取の傾向を厳しく批判的に分析している。万葉集や『古事記』への復古的傾斜は、プロレタリア文学の退潮に伴う社会的不安への反動として現れつつあるが、単なる懐古主義に過ぎず、現代社会の現実から遊離していると指摘する。特に、国文学の伝統的な閉鎖性や社会性欠如が、特定の知識人層によって古典を「精神的な安らぎの場」として利用する「安全地帯」を創出し、大衆的な批判を免れている実態を曝く。また、「さび」や「いき」などの美的感覚は、本来の市民生活から乖離し、ブルジョア階級や骨董屋を介して消費される様式化されたものとなり、貧困な文明の反映であるとする見方への反論も交えて論じられる。最後に、日本の創作に根付く「勘」という概念を封建的・職人的な閉鎖性の産物として再検証し、歴史性や社会性による客観的検証を怠り、個人の直感や主観的自信に頼る傾向が、思想性を喪失した文学の現状において危険な回避行動であるとしている。"
    }
  },
  "overall": {
    "summary": "一九三七年三月、語り手は現代日本文学における古典摂取の傾向を厳しく批判的に分析する。万葉集や『古事記』への復古的傾斜は、プロレタリア文学の退潮に伴う社会的不安への反動として現れるが、単なる懐古主義に過ぎず、現代社会の現実から遊離していると指摘される。国文学の伝統的な閉鎖性や社会性の欠如が、特定の知識人層によって古典を「精神的な安らぎの場」とする「安全地帯」を創出し、大衆的な批判を免れている実態が曝き出される。また、「さび」や「いき」などの美的感覚は、本来の市民生活から乖離し、ブルジョア階級や骨董屋を介して消費される様式化されたものとなり、貧困な文明の反映という見方への反論も交えつつ論じられる。最後に、日本の創作に根付く「勘」という概念を封建的・職人的な閉鎖性の産物として再検証し、歴史性や社会性による客観的検証を怠り、個人の直感や主観的自信に頼る傾向が、思想性を喪失した文学の現状において危険な回避行動であるとして警告を呈する。",
    "tags": {
      "ジャンル": [],
      "時代": [
        "昭和文学"
      ],
      "文学運動・流派": [],
      "テーマ": [
        "社会批評・風刺",
        "知識人の苦悩"
      ],
      "形式・文体": [
        "評論・批評"
      ]
    }
  }
}