{
  "book_id": 185,
  "title": "さまよえる猶太人",
  "author": "芥川竜之介",
  "translator": null,
  "country": "日本",
  "publication_year": 1917,
  "summary": "ヨーロッパの伝説「さまよえるユダヤ人」を題材にした作品です。イエスが磔刑に向かう途中、ユダヤ人ヨセフが彼を罵倒し暴行を加えたため、イエスの再臨まで死ぬことなく世界をさまよう呪いを受けたという伝説を扱っています。芥川は熊本で発見したという古文書「ふらんしす上人さまよえるゆだやびとと問答の事」を引用し、フランシスコ・ザビエルに供をしていたシメオン伊留満がこの呪われた存在と出会った際の問答を記録しています。作品は伝説の日本への伝播と、その文化的意味を創造的に解釈した歴史的エッセイの性質も持ちます。",
  "tags": {
    "ジャンル": [
      "短編小説",
      "評論・批評"
    ],
    "時代": [
      "大正文学"
    ],
    "文学運動・流派": [
      "新思潮派"
    ],
    "テーマ": [
      "宗教・信仰",
      "哲学・思想",
      "死・生死観"
    ],
    "形式・文体": [
      "書簡体・日記形式"
    ]
  },
  "source_urls": [
    "https://www.aozora.gr.jp/cards/000879/card185.html",
    "https://booklog.jp/item/7/000185"
  ],
  "generated_at": "2026-05-09T21:04:35.455779+00:00"
}