{
  "book_id": 1085,
  "title": "おきなぐさ",
  "author": "宮沢賢治",
  "translator": null,
  "country": "日本",
  "publication_year": null,
  "summary": "おきなぐさ（うずのしゅげ）という花を題材にした、宮沢賢治の詩的な散文作品です。黒く見えながらも太陽光が当たると赤く燃え立つように見えるこの花を愛する蟻や、その美しさに見とれて鳥を食べることすら忘れる山男の姿が描かれます。小岩井農場の野原で、二本のおきなぐさが春に花を咲かせ、夏には銀色の房に変わり、やがて風に乗って遠く旅立つまでの季節の移ろいが、詩情豊かに綴られています。自然観察と幻想的な表現が融和した、賢治独特の世界観を示す作品です。",
  "tags": {
    "ジャンル": [
      "散文詩",
      "童話・児童文学"
    ],
    "時代": [
      "昭和文学"
    ],
    "文学運動・流派": [],
    "テーマ": [
      "自然描写",
      "郷愁・ノスタルジア"
    ],
    "形式・文体": [
      "詩的散文"
    ]
  },
  "source_urls": [
    "https://www.aozora.gr.jp/cards/000081/files/1085_47131.html",
    "https://aozorashoin.com/title/1085"
  ],
  "generated_at": "2026-05-10T00:14:33.726018+00:00"
}