{
  "book_id": 235,
  "title": "八十八夜",
  "author": "太宰治",
  "translator": null,
  "country": "日本",
  "publication_year": 1939,
  "summary": "かつて「反逆的」で「ハイカラ」な作家として注目された笠井は、時とともに俗化してしまった自身に嘆きながら、長野県上諏訪へと向かいます。そこで女将と再会し楽しい時間を過ごしますが、翌朝の思わぬ情事の場面に別の女将が入ってきたことで、笠井の心身は完全に「糞リアリズム」へと堕ちていきます。本作は太宰の自伝的要素を含みながら、理想から現実へと転落していく知識人の内面的葛藤を、繊細かつ諧謔的に描いた秀作です。若き日の理想と現在の自分の乖離、そして人間の本質的な弱さと欺瞞を見つめる視点が特徴的です。",
  "tags": {
    "ジャンル": [
      "短編小説"
    ],
    "時代": [
      "昭和文学"
    ],
    "文学運動・流派": [
      "無頼派"
    ],
    "テーマ": [
      "知識人の苦悩",
      "人間の内面・自我",
      "心理描写",
      "ユーモア・滑稽"
    ],
    "形式・文体": []
  },
  "source_urls": [
    "https://www.aozora.gr.jp/cards/000035/files/235_20029.html",
    "https://ja.wikipedia.org/wiki/%E5%85%AB%E5%8D%81%E5%85%AB%E5%A4%9C_(%E5%B0%8F%E8%AA%AC)",
    "https://www.yomuhon.com/archives/4607"
  ],
  "generated_at": "2026-05-09T21:38:16.833715+00:00"
}