{
  "contents": {
    "content_0.html": {
      "headings": [],
      "summary": "語り手は、混雑する夏の旅行を嫌う一方で、自宅に籠もることを夏への最善の享楽と説く。静座や仰臥など、何も動かずに自然と痩せていく「干乾びた」状態を好み、それは冬の夜の静けさよりもむしろ「明るい」「ものなつかしい」と感じる。この無為の境地に立証するため、庭の草木や蜃気楼のような小動物との交流を愛し、暑さを忘れるための執筆環境も工夫している。また、夏特有の朝の静けさや、短夜のはかなさを詠みつつ、夏を去る土用の時期に吹く冷たい風（土用風）を以て秋の訪れを感ずる。夏と秋の境目において、蝉や鳥のさえずりが天地の霊性を感じさせる寂寥感と共に、人生の短さや移ろいの哀しみ、そして静かな寂寥を詠嘆する心情が描かれる。"
    }
  },
  "overall": {
    "summary": "本書は、夏を愛しつつもその激しさを避ける、静謐な作家の心情を詠った一篇である。著者は混雑を嫌い、自宅に籠もることを夏の至高の享楽とする。動かずに身を「干乾びた」状態へと委ね、草木や蜃気楼のような小動物との静かな交感を通じて、暑さを忘れる精神の自由を追求する。夏の朝の静けさや短夜のはかなさ、そして土用の冷風が秋の訪れを告げる瞬間に、蝉や鳥の声から天地の霊性を感じ取る。そこには、人生の儚さと移ろいの哀しみが静かに漂い、季節の巡り合いにおける寂寥感が深く詠嘆される。これは夏の喧騒を退け、内なる静寂の中で自然と対話し、生と死の狭間における静かなる感興を描く、散文詩のような作品である。",
    "tags": {
      "ジャンル": [
        "短編小説"
      ],
      "サブジャンル": [
        "叙情的"
      ],
      "時代": [],
      "文学運動・流派": [],
      "テーマ": [
        "自然描写",
        "死・生死観"
      ],
      "形式・文体": []
    }
  }
}