{
  "contents": {
    "content_0.html": {
      "headings": [],
      "summary": "この箇所は徳永直の小説『はたらく人々』における評者による批評である。主人公アサが、愛子やシゲといった対照的な女性像と対比されつつ、二重の負担に耐えながら「女文選」としての技術を習得し、古い慣習への抵抗として働き続ける姿が描かれると紹介される。しかし評者は、前半の勝気な少女から後半の技術と自覚に満ちた勤労婦人へと至るアサの精神的成長の必然性が描き切れていないと指摘する。特に、家族との軋轢や社会的圧力の中で彼女がなぜ「働くことが唯一の道」と確信に至ったのか、その内面的な転換点となる出来事が小説内で不明瞭であるとして疑問を呈する。後半の描写は作者の理想が投影された感があり、生彩あふれる細部描写の美しさは称賛しつつも、それが読者の実感に十分訴えかけるための人物や構造的な欠落が感じられると結論付けている。"
    }
  },
  "overall": {
    "summary": "徳永直の『はたらく人々』は、主人公アサという勤労女性を描いた作品である。アサは、愛子やシゲといった対照的な女性像を背景に、家族との軋轢や厳しい社会的圧力という二重の重圧に耐えながら生きていく姿が描かれている。彼女は古い慣習への抵抗として「働くこと」を選び、単なる少女から「女文選」としての技術と自覚を備えた勤労婦人へと成長していく過程が描かれる。作風としては、生彩あふれる細部描写が評価されるが、評者からは前半の勝気な少女から後半の確信ある勤労婦人への精神成長の必然性が十分描ききれていないとの指摘がある。特に、彼女がなぜ「働くことが唯一の道」と断固として確信に至ったのか、その内面的な転換点となる決定的な出来事が小説内で不明瞭であり、読者の実感に十分に訴えかける人物像や構成に欠落を感じさせるという批評がなされている。作者の理想が投影された後半の描写は称賛されるものの、その不完全さが作品全体の魅力と相まって、働く女性の現実と葛藤を描く一つの文学的試作として注目に値する作品である。",
    "tags": {
      "ジャンル": [
        "中編小説"
      ],
      "サブジャンル": [
        "大衆小説"
      ],
      "時代": [
        "昭和文学"
      ],
      "文学運動・流派": [],
      "テーマ": [
        "家族・人間関係",
        "女性の生き方",
        "社会批評・風刺"
      ],
      "形式・文体": []
    }
  }
}