{
  "contents": {
    "content_0.html": {
      "headings": [],
      "summary": "中国の田舎に住む若い書生が、隣に一人暮らす謎めいた美女に疑問を抱く。ある春の暮れ、書生が彼女の罵声を聞いて様子を見に行くと、彼女が年寄り（木こり）を殴打している現場に出くわす。書生が年長者を叱るべきだと諫めるが、彼女は「木こりは自分が年下」と言い返し、さらに「その木こりは自分の息子（倅）である」と告白する。書生は驚き、木こりが七十歳ほどなら母親の年齢を問う。女は「三千六百歳」と答え、書生は彼女が仙人だと気づく直後、彼女は神々しい姿で消え去る。残されたのは涙を流す木こりの老人だけだった。この一場面で、書生は超自然的な存在との遭遇を通じて、常識にとらわれない生命の重さと老いの姿を直視することになる。語り手は三人称の全知視点で、書生の心理描写と情景を客観的に描き出している。"
    }
  },
  "overall": {
    "summary": "中国の田舎を舞台に、隣家に独居する謎めいた美女を不思議がる若い書生が描かれる。ある春の暮れ、書生は彼女が老いた木こりを殴打する現場を目撃し、年長者への礼儀を諫めるが、女は「木こりは自身の息子である」と告げる。さらに、七十歳の老人の母でありながら三千六百歳を持つ彼女こそが仙人であることを明かすと、神々しい姿で消え去る。残された老木こりと、超自然的な存在との邂逅を通じ、常識や年齢の概念を超越した生命の重さ、そして老いにおける親子の業の深さを突きつけられる書生の姿が描かれる。物語は三人称全知視点によって進行し、書生の驚愕と内面的な変容が客観的かつ劇的に描き出される。仙人との一瞬の遭遇が、単なる怪異譚を超え、人間の存在意義や死生観への問いかけへと昇華される点に、この作品の核心的な魅力がある。",
    "tags": {
      "ジャンル": [
        "幻想・怪奇小説"
      ],
      "時代": [],
      "文学運動・流派": [],
      "テーマ": [
        "死・生死観",
        "人間の内面・自我",
        "家族・人間関係"
      ],
      "形式・文体": [
        "心理描写"
      ]
    }
  }
}