{
  "contents": {
    "content_0.html": {
      "headings": [],
      "summary": "この箇所の要約は以下の通りです。\n\n石坂洋次郎の『若い人』への読後感を基に、作者が主人公を「東京へ逃す」という終結の手法が、地方から都会への逃避そのものであり、作者自身の文学的・思想的な限界や降服の旗印であることを指摘する。石坂の作品世界は、地方の文化的暗闇の中で確信に満ちた孤独な明かりのようなものだったが、上京後の作品は土を失い乾燥化し、幻想が失われた状態にあると分析する。さらに中村武羅夫の「文学の地方分散」論に触れ、朝鮮・九州等の地方文学の活発さを評価しつつ、農民作家や地方作家が単に故郷へ帰還するだけでは不十分であると説く。各地の職業や生活の具体性を歴史的・社会的に把握し、単なる素材主義やローカルな情緒に留まらない高みへ作品を昇華させることが、中央文壇の崩壊を補完し、日本文学に多極性と豊かさをもたらす鍵であると論じ concludes。一九四〇年七月の文芸評論として、文学の地方分散が持つ文化的意義と課題を深く考察している。"
    }
  },
  "overall": {
    "summary": "本作品は、一九四〇年七月に発表された石坂洋次郎の『若い人』に関する鋭い文学評論である。著者は、同作の結末において主人公が東京へ逃れる展開を、地方から都会への逃避と捉え、作者の思想的・文学的限界を示すものとして批判的に分析する。石坂の地方描写が抱えた暗闇と孤独の輝きは、上京後の作品では土を失い乾燥化し、幻想を欠いたものと指摘される。\n\nしかし本稿の核心は、これに留まらない。中村武羅夫の「文学の地方分散」論を軸に、朝鮮や九州など地方文学の活発な展開を高く評価しつつ、単なる郷土回帰や情緒的懐古に終わらせないよう警告する。各地域の職業や生活の実相を歴史的・社会的に深く把握し、素材主義の域を超えて作品を昇華させることが、中央文壇の崩壊を補完し、日本文学に多様性と豊かさを付与する鍵であると論じる。文学のあり方について、地方の可能性と課題を重く思索した重要な一節である。",
    "tags": {
      "ジャンル": [
        "評論・批評"
      ],
      "サブジャンル": [],
      "時代": [
        "昭和文学"
      ],
      "文学運動・流派": [],
      "テーマ": [
        "知識人の苦悩",
        "社会批評・風刺",
        "死・生死観"
      ],
      "形式・文体": [
        "散文詩"
      ]
    }
  }
}