{
  "contents": {
    "content_0.html": {
      "headings": [],
      "summary": "提供されたテキストは『美濃部民子夫人に献ず』という献辞（タイトルページまたは序章冒頭の別頁）のみであり、物語のあらすじや情景描写、登場人物の心情といった具体的な内容は含まれていません。献辞は特定の人物（美濃部民子夫人）への敬意表明であり、物語の展開、語り手の視点、状況の変化を示す要素を欠いています。したがって、前章との継続性や物語内の具体的な出来事について要約することはできません。この箇所の機能は、作品が誰のために捧げられたかを示す形式的な要素に留まります。"
    },
    "content_1.html": {
      "headings": [
        "自序"
      ],
      "summary": "この「自序」において、語り手である與謝野晶子は、明治三十三年から近年までの詩四二一篇を精選して編んだ詩集の刊行にあたり、美濃部民子夫人への献辞を記述している。晶子は、夫人が毎年の春から冬にかけて自ら採りたてた薔薇を頻繁に贈り、自身の精神を励まし和らげてくれたことに深く感謝し、この詩集をそのお礼として捧げようとする。作中には、夫人から贈られる「みづみづしい」薔薇への畏敬の念と、自身の手編みの詩集が決して夫人の贈り物には及ばないという謙虚な姿勢が描かれている。また、詩集は「全集」と銘打たれているが、元来は二百篇ほどが失われたり省略されたものであり、年代順ではなく心情で分類された非統一の構成であることは、詩人の心の姿そのものであると説明されている。装幀には山下新太郎先生が務めており、その点を友人や読者への共有の喜びとして言及している。"
    },
    "content_2.html": {
      "headings": [
        "雲片片",
        "（小曲五十六章）",
        "草と人",
        "鼠",
        "賀川豐彦さん",
        "人に答へて",
        "晩秋の草",
        "書斎",
        "我友",
        "恋",
        "己",
        "おの",
        "が",
        "路",
        "みち",
        "また人に",
        "車の跡",
        "繋縛",
        "帰途",
        "拍子木",
        "或夜",
        "あるよ",
        "堀口大學さんの詩",
        "岬",
        "静浦",
        "牡丹",
        "弓",
        "秋思",
        "園中",
        "人知らず",
        "飛行船",
        "柳",
        "易者に",
        "甥",
        "花を見上げて",
        "我家の四男",
        "正月",
        "唯一",
        "ゆひいつ",
        "の",
        "問",
        "とひ",
        "秋の朝",
        "秋の心",
        "今宵の心",
        "我歌",
        "憎む",
        "悲しければ",
        "緋目高",
        "ひめだか",
        "涼夜",
        "りやうや",
        "卑怯",
        "水楼にて",
        "批評",
        "過ぎし日",
        "春風",
        "はるかぜ",
        "或人の扇に",
        "桃の花",
        "杯",
        "さかづき",
        "日和山",
        "ひよりやま",
        "春草",
        "しゆんさう",
        "二月の雨",
        "秋の柳",
        "冬のたそがれ",
        "惜しき頸輪",
        "思",
        "おもひ",
        "は長し",
        "蝶",
        "欲望"
      ],
      "summary": "このセクションは、詩集『雲片片』より「草と人」から「欲望」に至る多数の短詩が列挙された部分である。語り手は、風に応じて動く草と自らの心に従う人間の対比や、天井裏の鼠の音と自身の詩作活動を重ね合わせることで、孤独と創作の緊張感、あるいは日常の中の非日常を詠み上げる。また、賀川豐彦への敬意や、文学者・友人たちとの精神的交流、自らの恋を「塔」に喩えた深い情念が描かれる。特に後段では、民衆の中に在るべきか外れるかという社会的・道徳的問いかけや、革命への憧憬、そして「多くのものを得ようとするが故に、及ばぬ方に手を伸ばす」という渇望と葛藤が鋭く描かれる。視点は一貫して第一人称の抒情詩的語り手にあり、四季の景物や具体的な人物像を通じて、内面の揺らぎと外世界への関与の狭間で揺れ動く詩人の魂が断片的に、しかし強烈に浮き彫りにされている。"
    },
    "content_3.html": {
      "headings": [
        "小鳥の巣",
        "（押韻小曲五十九章）"
      ],
      "summary": "この部分は、詩集『雲片片』の「押韻小曲五十九章」として、作者が自ら「押韻の法」を追求する試作詩群を収録したものである。小序において、自由詩の不安定さを補うため、漢詩や西洋詩の韻律を参照しつつ、内心の自律的発展に基づき推敲を加えた経緯が述べられる。詩篇の内容は、砂掘る行為や腐敗する林檎、小鳥の巣などの自然景物から、戦争や貧困、労働運動などの社会情勢、そして恋や死への希求まで、多岐にわたる。語り手は「もろい鑿」を自らの表現能力に喩えつつ、泥にまみれた郊外や雪の峰など、荒々しい現実と美しき夢の狭間で揺れる心情を詠う。特に、すべての人への愛と一人への背反という矛盾、言葉の無力感と歌による救済の希求など、内面の葛藤と社会への関心が激しく交錯する。視点は一貫して第一人称の抒情詩的語り手であり、その内面と外部世界との緊張関係が、季節の移ろいや具体的なイメージを通じて断片的だが強烈に浮き彫りにされる展開である。"
    },
    "content_4.html": {
      "headings": [
        "夢と現実",
        "（雑詩四十章）",
        "明日",
        "肖像",
        "読後",
        "紅い夢",
        "アウギユスト",
        "産室",
        "うぶや",
        "の",
        "夜明",
        "よあけ",
        "颱風",
        "冬が始まる",
        "木下杢太郎さんの顔",
        "母ごころ",
        "我子等よ",
        "親として",
        "正月",
        "大きな黒い手",
        "絵師よ",
        "戦争",
        "歌はどうして作る",
        "新しい人人",
        "黒猫",
        "曲馬の馬",
        "夜の声",
        "自問自答",
        "我が泣く日",
        "伊香保の街",
        "市に住む木魂",
        "Ｍ氏に",
        "詩に",
        "就",
        "つ",
        "いての",
        "願",
        "ねがひ",
        "宇宙と私",
        "白楊のもと",
        "わが髪",
        "坂本紅蓮洞さん",
        "焦燥",
        "せうさう",
        "人生",
        "或る若き女性に",
        "君死にたまふことなかれ",
        "（旅順の攻囲軍にある弟宗七を歎きて）",
        "梅蘭芳に",
        "京之介の絵",
        "（少年雑誌のために）",
        "鳩と京之介",
        "（少年雑誌のために）"
      ],
      "summary": "本段落は、詩人による「夢と現実」「明日」「肖像」「読後」など、多様な詩篇から構成される。語り手は「明日」への希求と、それが平凡な昨日に過ぎ去ることへの幻滅というジレンマを描きつつ、その矛盾に耐えながら歌い続ける決意を示す。続く「肖像」では、悲しみに沈んだ女の像を画家に託し、その運命の剥落を暗示する。また、夏目漱石やゾロアスター教への言及、そして自身の「紅い夢」の希求が綴られる。特に「産室」「冬が始まる」の節では、死の苦しみから生還した母としての体験と、冬という厳しい季節がもたらす精神の試練や活動への賛美が交錯する。戦争への激しい批判と、その中での生命の再生への希望、さらに「梅蘭芳」や「京之介」への献詩など、芸術や友情への愛情、社会への鋭い眼差しが、抒情と社会批評の狭間で激しく揺れ動く。視点は一貫して第一人称の抒情詩的語り手であり、内なる葛藤と外なる現実の緊張関係が、季節や具体的なイメージを通じて断片的かつ強烈に浮き彫りにされる展開である。"
    },
    "content_5.html": {
      "headings": [
        "Ａの字の歌",
        "（少年雑誌のために）",
        "蟻の歌",
        "（少年雑誌のために）"
      ],
      "summary": "前段で描かれた芸術への愛着や社会への眼差しに続き、この箇所では具体的な物語と童詩的視点へ転換する。まず、嵐に傷つけられた白鳩を拾い上げ、人知れず抱き守る少年・京之介の姿が描かれる。彼が腕白どもに「供くれ」と迫られても大人のように沈着して拒否する様は、彼の優しさと内面的な強さを象徴的に浮き彫りにする。\n\n次に、語り手は「A の字の歌」により、その形状に込められた多様なイメージを連想する。掘立小屋の入り口から灯台、琴柱、水晶のプリズム、大歩で進む人、ピラミッド、そして道化師に至るまで、A の字が持つ静寂、希望、活力、威厳、孤独を次々と展開させ、言葉の持つ視覚的・精神的広がりを讃える。最後に「蟻の歌」では、黒い蟻の行列を「8 の字」に見立て、太陽の下で怠らず進み続けるその姿を「元気な少年隊」として賛美する。全篇を通じて、語り手は対象への深い共感と、生命の持つ健全な活力への肯定的な眼差しを維持している。"
    },
    "content_6.html": {
      "headings": [
        "壺の花",
        "（小曲十五章）",
        "コスモス",
        "手",
        "著物",
        "朱",
        "独語",
        "どくご",
        "螇蚸",
        "ばつた",
        "蚊",
        "蛾",
        "朝顔",
        "蝦蟇",
        "がま",
        "蟷螂",
        "かまきり",
        "玉虫",
        "寂寥",
        "せきれう",
        "小鳥の巣",
        "末女",
        "すゑむすめ"
      ],
      "summary": "この段落は、石川啄木が「壺の花」より採った短歌および随想風の詩篇群である。語り手はコスモスに太陽が沈む情景や、労働の尊厳を込めた農民の「手」、朝鮮人蔘にたとえた手触りを描き、物質的・生命的な現実を直視する。また、朱を擦る行為からパリの霧や楊貴妃を想起する夢幻的な瞬間、バスチユの脱獄に例えた虫の反抗、蚊や蛾を通じて人間の臆病や宿命を照らし出す。さらに蟷螂の雌が雄を喰らう様を「女性専制」に喩え、玉虫の飼育が失われたことへの近代化の寂寥感を嘆く。終始貫かれるのは、筆執り歌おうとも払拭できぬ深淵な「寂寥」の心情である。最後の「末女」において、夜中に蒲団が落ちたと母を呼ぶ九歳の藤子の姿が描かれ、全編の重厚な思索と孤独に、静かなる日常の温かさと切なさを添える。視点は一貫して語り手の内面から、対象への共感的かつ批評的な眼差しへと変動する。"
    },
    "content_7.html": {
      "headings": [
        "薔薇の陰影",
        "（雑詩廿五章）",
        "屋根裏の男",
        "或女",
        "あるをんな",
        "椅子の上",
        "馬場孤蝶先生",
        "故郷",
        "自覚",
        "約束",
        "涼夜",
        "りやうや",
        "渋谷にて",
        "浜なでしこ",
        "恋",
        "夏の宵",
        "如何に若き男",
        "男",
        "夢",
        "男の胸",
        "鴨頭草",
        "つきくさ",
        "月見草",
        "伴奏",
        "初春",
        "はつはる",
        "仮名文字",
        "子守",
        "寂しき日",
        "煙草",
        "百合の花"
      ],
      "summary": "この部分は、屋根裏の部屋で男女が出会う情景から始まり、舞妓の女性への共感、恋人を待つ切ない心情、そして石川啄木と馬場孤蝶の師弟関係への敬意を描く。故郷への懐古や、死を覚悟する男との出会いによる覚醒、約束と裏切りの苦悩、寄席の寂寥感、病める子の姿など、貧困と死、孤独、そして日常の断片が交錯する。語りが多角的に変化し、特定の「男」や「女」の視点から、普遍的な人間の哀歓へと広がり、最後に百合の花を「侯爵夫人」に喩え、清らかな愛と世界への共感的な愛への昇華へと至る。"
    },
    "content_8.html": {
      "headings": [
        "月を釣る",
        "（小曲卅五章）",
        "釣",
        "人中",
        "炎日",
        "月見草",
        "明日",
        "芸術",
        "力",
        "走馬灯",
        "空しき日",
        "麦わら",
        "恋",
        "対話",
        "或女",
        "爪",
        "或国",
        "朝",
        "或家のサロン",
        "片時",
        "春昼",
        "しゆんちう",
        "雪",
        "猫",
        "或手",
        "通り雨",
        "春の夜",
        "牡丹",
        "女",
        "鬱金香",
        "文の端に",
        "教会の窓",
        "裏口へ来た男",
        "髪",
        "磯にて",
        "九段坂",
        "年末",
        "市上"
      ],
      "summary": "この箇所は、夏や雪、花などの自然景物を通じて、語り手（主に女性）の孤独と憂いを詠み上げる小曲群から構成されています。炎暑で猫が死に絶える庭や、月見草、雪の寂寥感などが描かれる一方、女が王よりも贅沢で精神的に優越していると賛美する直情的な「女」の詩や、明治の風俗を風刺する「或国」「市上」など、社会批判の視点も交じります。語り手は、愛する人への憧憬、日常の些細な情景からの懐古、そして時代への虚無感や怒りを、月釣りのような詩的比喩と生々しい描写で綴り、個人の感情と社会のあり方を対比させながら、芸術と「力」への志向へと精神を向けています。"
    },
    "content_9.html": {
      "headings": [
        "第一の陣痛",
        "（雑詩四十一章）",
        "第一の陣痛",
        "アウギユストの一撃",
        "日曜の朝飯",
        "駆け出しながら",
        "三つの路",
        "錯誤",
        "途上",
        "旅行者",
        "何かためらふ",
        "真実へ",
        "森の大樹",
        "我は雑草",
        "子供の踊（唱歌用として）",
        "砂の上",
        "三十女の心",
        "わが愛欲",
        "今夜の空",
        "日中の夜",
        "人に",
        "寂寥",
        "自省",
        "山の動く日",
        "一人称",
        "乱れ髪",
        "薄手の鉢",
        "剃刀",
        "煙草",
        "女",
        "大祖母の珠数",
        "我歌",
        "すいつちよ",
        "油蝉",
        "雨の夜",
        "間問題",
        "現実",
        "饗宴",
        "歯車",
        "異性",
        "わが心",
        "儀表",
        "ぎへう",
        "白蟻"
      ],
      "summary": "この箇所は、第一の陣痛を通じて生命の創造と苦痛を直面する語り手の内面、およびその先に見出される力への志向を描く一連の詩的断片から成る。冒頭、「第一の陣痛」において語り手は分娩の激痛と恐怖に震えつつも、それを「真実創造」として絶対的価値を見出し、孤独に耐え抜く決意を固める。続く「アウギユストの一撃」では、幼子の手による母への打撃を、未来における純粋な征服力や生命の躍動の予感として肯定的に捉え、自己の生命力を子に重ねている。その後、家族の日常的な朝食から始まり、現代社会の肉体的・精神的制約からの脱却と、芸術・思想・戦争などあらゆる要素を統合する「大建築」への舞踊的変容を希求する。しかし、三つの路（ニーチェ・トルストイ・ドストエフスキー）に迷う中で、語り手は孤独と戦慄を抱えつつも「真実へ」歩み出し、森の大樹に象徴される苦痛の受容と、自身の「雑草」としての生命力を歌い上げる。全体を通して、個人の内面の葛藤と、時代への批判的視点、そして破壊と創造を伴う絶対的な力への衝動が、抒情と比喩を駆使して激しく交錯する。語り手の視点は、出産という生理的事象から始まり、普遍的な人間存在の苦悩と希望へと拡大し続ける。"
    },
    "content_10.html": {
      "headings": [
        "幻想と風景",
        "（雑詩八十七章）",
        "曙光",
        "大震後第一春の歌",
        "元朝の富士",
        "伊豆の海岸にて",
        "田舎の春",
        "太陽出現",
        "春が来た",
        "二月の街",
        "我前に梅の花",
        "紅梅",
        "新柳",
        "牛込見附外",
        "市中沙塵",
        "弥生の歌",
        "四月の太陽",
        "雑草",
        "桃の花",
        "春の微風",
        "桜の歌",
        "緋桜",
        "ひざくら",
        "春雨",
        "薔薇の歌（八章）",
        "牡丹の歌",
        "初夏",
        "はつなつ",
        "夏の女王",
        "五月の歌",
        "五月",
        "礼讃",
        "らいさん",
        "南風",
        "五月の海",
        "チユウリツプ",
        "五月雨",
        "夏草",
        "たんぽぽの穂",
        "屋根の草",
        "五月雨と私",
        "隅田川",
        "朝日の前",
        "虞美人草",
        "罌粟の花",
        "散歩",
        "夏日礼讃",
        "庭の草",
        "暴風"
      ],
      "summary": "この部分では、地震や大火という破壊的出来事の後の再生と、新世紀（1919 年）の黎明を祝う詩的断片が続く。語り手は、太陽や春の訪れを「不死鳥」や「若き青年」といったイメージで捉え、過去の死旧や社会の弊害を断ち切り、愛・真実・労働を織り交ぜた「大建築」の建設への決意を示す。特に、富士山を「新しき世界の噴火」として捉える視点は、過去から未来への飛躍を象徴している。また、椿、梅、桜、薔薇、牡丹、春の草花など、多様な自然の意象が、人間の情感や生命の躍動、あるいは「雑草」のような屈強な生存本能と重ね合わせられている。五月に至っては、官能的で熱狂的な生命力の頂点として描かれ、海や祭りのイメージと共に、沈滞からの脱却と万物が一つになる「太陽の月」へと変容する。語り手の視点は、個人の内面的な苦悩や孤高の情念から、社会全体や自然界全体を包含する普遍的な生命への賛美へと広がり、破壊と創造を繰り返す絶対的な力への歓喜が、色彩豊かで激しい比喩の連なりの中で表現される。"
    },
    "content_11.html": {
      "headings": [
        "すいつちよ",
        "上総の勝浦",
        "木",
        "こ",
        "の",
        "間",
        "ま",
        "の泉",
        "草の葉",
        "蛇",
        "蜻蛉",
        "とんぼ",
        "夏よ",
        "夏の力",
        "大荒磯崎にて",
        "女の友の手紙",
        "涼風",
        "地震後一年",
        "古簾",
        "虫干の日に",
        "机に",
        "凭",
        "よ",
        "りて",
        "蜂",
        "わが庭",
        "夏の朝",
        "蝉",
        "新秋",
        "初秋",
        "はつあき",
        "の歌",
        "初秋の月",
        "優しい秋",
        "コスモスの花",
        "秋声",
        "秋",
        "街に住みて",
        "郊外",
        "海峡の朝",
        "秋の盛り",
        "朝顔の花",
        "晩秋",
        "電灯",
        "腐りゆく匂ひ",
        "十一月",
        "冬の木",
        "落葉",
        "冬の朝",
        "腐果",
        "冬の一日",
        "冬を憎む歌",
        "白樺",
        "雪の朝",
        "雪の上の鴉"
      ],
      "summary": "前段の「再生への決意」から、語り手は季節の移ろいと自然の細部を捉え、内省的かつ官能的な観察へと視点を移す。激しい夏や雄大な海、そして慈愛に満ちた秋は、生命の躍動と美しさを謳う一方、冬への移行と共に恐怖、死、病、そして震災（1923 年大正関東地震）の爪痕が顕在化する。語り手は「蛇」や「冬」を嫌悪する二元論者となりつつ、枯れた自然や震災の廃墟の中に「死への忍耐」と「再生の予感」を見出そうとする。最終的に、雪景色に佇む黒い鴉は、荒廃した世界を象徴する「黒い文字」のように描かれ、絶望と静かな生存意志の対比によって、物語は冷徹な終焉の空気の中で閉じられる。"
    },
    "content_12.html": {
      "headings": [
        "西土往来",
        "（欧洲旅行前及び旅中の詩廿九章）",
        "別離",
        "別後",
        "べつご",
        "ひとり寝",
        "東京にて",
        "図案",
        "旅に立つ",
        "子等に",
        "巴里より葉書の上に",
        "エトワアルの広場",
        "薄暮",
        "はくぼ",
        "ヹルサイユの逍遥",
        "仏蘭西の海岸にて",
        "フオンテンブロウの森",
        "巴里郊外",
        "ツウル市にて",
        "セエヌ川",
        "芍薬",
        "ロダンの家の路",
        "飛行機",
        "モンマルトルの宿にて",
        "暗殺酒鋪",
        "キヤバレエ・ダツサツサン",
        "（巴里モンマルトルにて）",
        "驟雨",
        "巴里の一夜",
        "ミユンヘンの宿",
        "伯林停車場",
        "和蘭陀の秋",
        "同じ時",
        "覉愁",
        "きしう",
        "モンソオ公園の雀"
      ],
      "summary": "語り手は愛する夫と神戸で別れ、一人巴里へ旅立つ。別れの際の絶望的な別離の悲しみと、夢の中で見る愛人の死を予感させる恐怖が描かれる。巴里では、凱旋門広場の激しい交通を「人間の業」の如く体験し、ルーブルやヴェルサイユの歴史の虚しさ、エデンの園のような海岸の美しさなどを通じて、自然と人間の対比や、夫への渇望と自己の存在感を確認する。ミユンヘンやベルリンの厳格で力強い駅の様子は、現代的な生命の躍動を表し、和蘭陀（オランダ）の美しい夕景には、故郷の子供たちへの思念が重なる。最終的にモンソオ公園の雀に対し餌をやる情景から、かつて筆一筋に没頭していた自分と対比させ、育児や日常の温かさを再認識する心境の変化が示される。"
    },
    "content_13.html": {
      "headings": [],
      "summary": "モンソア公園で雀に餌を与えていた語り手は、ふと幼い頃の童謡「雀すずめ」を口ずさみ、自身の心象を投影する。そこでは、育児に捧げるべき時間を旅に費やした罪悪感、筆に没頭する旧我への自己批判が激しく渦巻く。しかし、雀が突然飛び去ったことをきっかけに、語り手の心境は劇的に転じる。直前に「みんなあなたのせいだ」と語りかけていた虚構の存在（おそらく幻視される夫や過去の自分）への怒りと失望が現れ、その存在が去ったことで、語る対象を失った虚脱感に陥る。最終的に、語り手は日本への帰国を強く誓い、絵を描くことさえ拒絶する。これは、旅の娯楽や芸術への執着を放棄し、母としての責任と日常の温かさに完全に回帰する決意表明であり、視点は一時的な思索から、切実な決断へと硬質化している。"
    },
    "content_14.html": {
      "headings": [
        "冷たい夕飯",
        "（雑詩卅四章）",
        "我手の花",
        "一すぢ残る赤い路",
        "砂の塔",
        "古巣より",
        "人の言葉",
        "闇に釣る船",
        "（安成二郎氏の歌集「貧乏と恋と」の序詩）",
        "灰色の一路",
        "厭な日",
        "風の夜",
        "小猫",
        "記事一章",
        "砂",
        "怖ろしい兄弟",
        "駄獣",
        "だじう",
        "の",
        "群",
        "むれ",
        "或年の夏",
        "三等局集配人（押韻）",
        "壁",
        "不思議の街",
        "女は掠奪者",
        "冷たい夕飯",
        "真珠貝",
        "浪のうねり",
        "夏の歌",
        "五月の歌",
        "ロダン夫人の賜へる花束",
        "暑き日の午前",
        "隠れ蓑",
        "夜の机",
        "きちがひ茄子",
        "花子の歌四章（童謡）",
        "九官鳥"
      ],
      "summary": "このテキストは、前節の「母としての責任への回帰」という決意とは対照的に、語り手が直面する極度の貧困と精神的苦悩を詩篇や短編風の断章群として描き出したものである。「冷たい夕飯」において、子供たちの生日を喜ばせることのできない親の惨めさと、家族の飢餓への恐怖が赤裸々に描かれている。語り手は、文学や芸術における「砂の塔」の虚構や、百貨店での「女は掠奪者」という自虐的自省を通じて、経済的基盤の欠如と社会的な無価値感に苦しむ。特に「灰色の一路」や「駄獣」の群れは、政治的な腐敗や貧困層の搾取を象徴し、語り手は自身を「貧しき生れ」として卑屈さと絶望の中に置く。一方で、「不思議の街」のようなユートピア的描写や、ロダン夫人から贈られた枯れた花束への懐かしみといった、美と救済を希う瞬間も存在する。これは、前節の決意が現実の生々しい苦しみによって揺らぎ、あるいはその苦しみの中で真摯に自己問答を繰り返している状態を示しており、視点は一貫して内省的かつ悲劇的な自省の姿勢を維持している。"
    },
    "content_15.html": {
      "headings": [
        "薔薇と花子",
        "花子の熊",
        "蜻蛉",
        "とんぼ",
        "の歌",
        "手の上の花",
        "一隅",
        "いちぐう",
        "にて",
        "午前三時の鐘",
        "或日の寂しさ"
      ],
      "summary": "この部分は、前節までの絶望的な自省とは対照的に、童謡風のリズムと擬人化による柔らかな世界観を持つ詩篇群から構成される。語り手（あるいは「花子」という擬人された視点）は、九官鳥の悪戯、花子の庭の薔薇や熊、蜻蛉の来訪といった小物との触れ合いを通じて、一時的に心の安らぎと美の世界を見出す。特に、自然と人間の感情が同調する描写や、孤独な存在への共感（鴨頭草）は、内省の静寂を強調している。\n\nしかし、終盤に差し掛かると状況は一変する。語り手は「片隅」に孤立し、飢えや鎖に例えられる苦痛を描写する。そして、上野の鐘を機に、日本人の無自覚な受容性や「うそ」に満ちた社会への批判的視点を再び開示する。終結では、昭代（昭和元年）の大典を迎える世情への複雑な心情を吐露し、虚構への批判と自己の限界を認めながら全集を終える。全体的に、幻想と現実の往復を繰り返しながら、悲観的かつ深い自覚を持つ視点の一貫性が保たれている。"
    }
  },
  "overall": {
    "summary": "与謝野晶子の詩集『雲片片』は、献辞から始まる詩群が、母としての陣痛の苦悩や生命への歓喜、自然の風景、海外旅行での観測、そして社会の貧困や戦争への批判など多岐にわたる主題を詠み上げる。語り手は、日常の断片から哲学的・社会的な深淵までを自由奔放に結びつけ、内なる葛藤と「真実」を求め続ける芸術家としての姿勢を一貫させる。抒情の美しさと社会への鋭い眼差しが交錯し、個人の内面と外部世界との緊張関係を詩的比喩で浮かび上がらせる。四季の移ろいや具体的な人物像を通じて、孤独、死、再生、そして芸術への絶対的な衝動が激しく交錯する晶子の魂の記録として、読み手には生命の躍動と人間の哀歓の重みを感じさせる。特に、母としての責任と芸術家としての自己の狭間で揺れ動きつつも、最後には日常と社会への深い共感へと至る精神的変容が、作品の核心をなしている。",
    "tags": {
      "ジャンル": [
        "短編小説"
      ],
      "時代": [
        "大正文学",
        "昭和文学"
      ],
      "文学運動・流派": [],
      "テーマ": [
        "心理描写",
        "社会批評・風刺",
        "家族・人間関係",
        "女性自身の生き方",
        "自然描写",
        "孤独・疎外",
        "死・生死観",
        "芸術・創作論"
      ],
      "形式・文体": [
        "連作短編",
        "詩的散文"
      ]
    }
  }
}